Workbook

Sheet Leia-me
A1: SkillWay — Plano de Vendas & Planejamento Financeiro
A2: Modelo de comprovação numérica · dados fictícios, mas calibrados em benchmarks reais do setor
B5: O que é este arquivo | C5: Todos os números citados na documentação do projeto (Plano de Vendas, Planejamento Financeiro, SOM) são recalculados aqui mês a mês, a partir de premissas explícitas — não são digitados soltos. Mude uma premissa na aba 'Premissas' e todo o resto do arquivo recalcula automaticamente.
B7: Natureza dos dados | C7: SkillWay ainda não tem receita real. Os números são fictícios (a empresa não existe fora deste projeto acadêmico), mas foram construídos para serem realistas: a conversão do funil, o CAC, o ticket médio e os custos fixos têm como referência benchmarks reais de SaaS B2B brasileiro, citados na aba 'Comparáveis de Mercado' e nas células de nota de cada premissa.
B9: Como navegar | C9: 1) Premissas — todas as variáveis de entrada, em uma só aba, com fonte/nota. 2) Funil de Vendas — leads, taxas de conversão e novos clientes fechados, mês a mês (Mês 1 a 24). 3) Receita e Clientes — clientes ativos, MRR e ARR mês a mês. 4) Custos Mensais — custo fixo por fase, CAC, custo de IA e comissão de vendas. 5) DRE Mensal — receita, custo, resultado operacional e caixa acumulado (mostra o mês exato do break-even). 6) Resumo Anual — Ano 1 x Ano 2 x Total 24 meses, no mesmo formato da Seção 20 da documentação. 7) Funil Padrão (Seção 19) — a tabela do funil em regime de maturidade, igual à da documentação. 8) Comparáveis de Mercado — as empresas reais usadas para calibrar as metas (com fonte).
B11: Código de cores | C11: Texto azul = premissa/entrada editável · Texto preto = fórmula (não editar) · Texto verde = referência a outra aba · Fundo amarelo claro = célula pensada para você testar outros cenários.
B13: Para comprovar um número da documentação | C13: Localize o mês ou o total correspondente nas abas 'Funil de Vendas', 'Receita e Clientes', 'Custos Mensais' ou 'DRE Mensal' — cada célula é uma fórmula rastreável até a premissa de origem.

Sheet Premissas
A1: Premissas do Modelo
A2: Toda variável de entrada do modelo vive nesta aba — mude aqui e o resto recalcula
B4: Premissa | C4: Valor | D4: Unidade | E4: Fonte / Nota
B5: PRODUTO & PRECIFICAÇÃO (Seção 19 — Plano de Vendas)
B6: Colaboradores médios por cliente | C6: 300 | D6: colaboradores | E6: Média assumida entre os 3 planos (Starter 100–300, Growth 301–800, Enterprise 801–2.000) — ponderada para o perfil de cliente-alvo do ICP (Seção 19).
B7: Preço médio por colaborador/mês | C7: 25 | D7: R$/colab/mês | E7: Média ponderada entre Starter R$29, Growth R$24 (plano de referência do SOM) e Enterprise R$19/colaborador/mês (Seção 19) — consistente com o R$25 usado no SOM (Seção 5).
B8: Ticket médio mensal por cliente | C8: =C6*C7 -> 7500 | D8: R$/mês | E8: Colaboradores médios × Preço médio por colaborador. Usado para converter clientes ativos em MRR.
B9: FUNIL DE VENDAS (Seção 19 — taxas de conversão)
B10: Taxa Lead → Lead Qualificado | C10: 0.2 | D10: % | E10: Benchmark típico de outbound B2B SaaS para PME (Seção 19).
B11: Taxa Qualificado → Demo agendada | C11: 0.4 | D11: % | E11: Idem.
B12: Taxa Demo → Proposta enviada | C12: 0.5 | D12: % | E12: Idem.
B13: Taxa Proposta → Cliente fechado | C13: 0.5 | D13: % | E13: Idem.
B14: Conversão geral (Lead → Fechado) | C14: =C10*C11*C12*C13 -> 0.02 | D14: % | E14: Produto das 4 taxas acima — a 100 leads/mês equivale a 2 clientes fechados/mês, igual à Seção 19.
B15: CUSTOS VARIÁVEIS (Seção 20 — benchmarks reais)
B16: CAC por cliente novo (fechado via funil) | C16: 3000 | D16: R$/cliente | E16: Piso da faixa PME (R$3–15 mil) citada nos benchmarks — Baita/Metrikia/BeansTech (Seção 20). Não se aplica aos clientes-piloto (captados por relação direta, sem custo de aquisição).
B17: Custo de processamento de IA por colaborador ativo/mês | C17: 0.5 | D17: R$/colab/mês | E17: Custo de infraestrutura de IA (inferência do motor de recomendação) por colaborador coberto pela plataforma.
B18: Comissão de vendas sobre a receita recorrente | C18: 0.05 | D18: % | E18: Comissão do time comercial sobre o MRR gerado no mês.
B19: CUSTOS FIXOS POR FASE (Seção 19 — fases do funil de vendas)
B20: Custo fixo mensal — Fase 1 · Piloto (M1–M3) | C20: 2500 | D20: R$/mês | E20: Equipe fundadora, infraestrutura básica em nuvem e ferramentas — sem contratações.
B21: Custo fixo mensal — Fase 2 · Early Adopters (M4–M9) | C21: 7000 | D21: R$/mês | E21: Ferramentas de vendas, Customer Success em regime parcial (Seção 19).
B22: Custo fixo mensal — Fase 3 · Scale inicial (M10–M18) | C22: 14000 | D22: R$/mês | E22: 1ª contratação de SDR ao atingir 10 clientes pagantes (Seção 19); infraestrutura escalando com a base.
B23: Custo fixo mensal — Fase 3 · Scale maduro (M19–M24) | C23: 19000 | D23: R$/mês | E23: Time comercial e de Customer Success completos.
B24: FASE PILOTO (Seção 18/19)
B25: Clientes-piloto (sem cobrança) | C25: 3 | D25: clientes | E25: 2 a 3 empresas parceiras no piloto (Seção 19) — adotado 3 para o cálculo.
B26: Mês de conversão do piloto em cliente pagante | C26: 4 | D26: mês | E26: Piloto roda M1–M3; os 3 clientes passam a pagar a partir do mês seguinte ao fim do piloto.
B27: META FINAL (Seção 5 — SOM)
B28: Meta de clientes ativos ao final de 24 meses (SOM) | C28: 40 | D28: clientes | E28: Igual ao SOM calculado no Dimensionamento de Mercado (Seção 5): 40 empresas em São Paulo.

Sheet Funil de Vendas
A1: Funil de Vendas — Mês a Mês (M1 a M24)
A2: Leads prospectados são a premissa de entrada; tudo abaixo é fórmula a partir das taxas de conversão (aba Premissas)
B4: Métrica | C4: M1 | D4: M2 | E4: M3 | F4: M4 | G4: M5 | H4: M6 | I4: M7 | J4: M8 | K4: M9 | L4: M10 | M4: M11 | N4: M12 | O4: M13 | P4: M14 | Q4: M15 | R4: M16 | S4: M17 | T4: M18 | U4: M19 | V4: M20 | W4: M21 | X4: M22 | Y4: M23 | Z4: M24 | AA4: Total 24m
B5: Mês nº | C5: 1 | D5: 2 | E5: 3 | F5: 4 | G5: 5 | H5: 6 | I5: 7 | J5: 8 | K5: 9 | L5: 10 | M5: 11 | N5: 12 | O5: 13 | P5: 14 | Q5: 15 | R5: 16 | S5: 17 | T5: 18 | U5: 19 | V5: 20 | W5: 21 | X5: 22 | Y5: 23 | Z5: 24
B6: Fase | C6: =IF(C5<=3,"Piloto",IF(C5<=9,"Early Adopters",IF(C5<=18,"Scale inicial","Scale maduro"))) -> Piloto | D6: =IF(D5<=3,"Piloto",IF(D5<=9,"Early Adopters",IF(D5<=18,"Scale inicial","Scale maduro"))) -> Piloto | E6: =IF(E5<=3,"Piloto",IF(E5<=9,"Early Adopters",IF(E5<=18,"Scale inicial","Scale maduro"))) -> Piloto | F6: =IF(F5<=3,"Piloto",IF(F5<=9,"Early Adopters",IF(F5<=18,"Scale inicial","Scale maduro"))) -> Early Adopters | G6: =IF(G5<=3,"Piloto",IF(G5<=9,"Early Adopters",IF(G5<=18,"Scale inicial","Scale maduro"))) -> Early Adopters | H6: =IF(H5<=3,"Piloto",IF(H5<=9,"Early Adopters",IF(H5<=18,"Scale inicial","Scale maduro"))) -> Early Adopters | I6: =IF(I5<=3,"Piloto",IF(I5<=9,"Early Adopters",IF(I5<=18,"Scale inicial","Scale maduro"))) -> Early Adopters | J6: =IF(J5<=3,"Piloto",IF(J5<=9,"Early Adopters",IF(J5<=18,"Scale inicial","Scale maduro"))) -> Early Adopters | ... Z6: =IF(Z5<=3,"Piloto",IF(Z5<=9,"Early Adopters",IF(Z5<=18,"Scale inicial","Scale maduro"))) -> Scale maduro
B7: Leads prospectados (entrada) | C7: 0 | D7: 0 | E7: 0 | F7: 0 | G7: 100 | H7: 50 | I7: 50 | J7: 100 | K7: 50 | L7: 100 | M7: 100 | N7: 100 | O7: 100 | P7: 100 | Q7: 100 | R7: 100 | S7: 100 | T7: 100 | U7: 100 | V7: 100 | W7: 100 | X7: 100 | Y7: 100 | Z7: 100 | AA7: =SUM(C7:Z7) -> 1850
B8: Leads qualificados | C8: =C7*Premissas!$C$10 -> 0 | D8: =D7*Premissas!$C$10 -> 0 | E8: =E7*Premissas!$C$10 -> 0 | F8: =F7*Premissas!$C$10 -> 0 | G8: =G7*Premissas!$C$10 -> 20 | H8: =H7*Premissas!$C$10 -> 10 | I8: =I7*Premissas!$C$10 -> 10 | J8: =J7*Premissas!$C$10 -> 20 | ... Z8: =Z7*Premissas!$C$10 -> 20 | AA8: =SUM(C8:Z8) -> 370
B9: Demos agendadas | C9: =C8*Premissas!$C$11 -> 0 | D9: =D8*Premissas!$C$11 -> 0 | E9: =E8*Premissas!$C$11 -> 0 | F9: =F8*Premissas!$C$11 -> 0 | G9: =G8*Premissas!$C$11 -> 8 | H9: =H8*Premissas!$C$11 -> 4 | I9: =I8*Premissas!$C$11 -> 4 | J9: =J8*Premissas!$C$11 -> 8 | ... Z9: =Z8*Premissas!$C$11 -> 8 | AA9: =SUM(C9:Z9) -> 148
B10: Propostas enviadas | C10: =C9*Premissas!$C$12 -> 0 | D10: =D9*Premissas!$C$12 -> 0 | E10: =E9*Premissas!$C$12 -> 0 | F10: =F9*Premissas!$C$12 -> 0 | G10: =G9*Premissas!$C$12 -> 4 | H10: =H9*Premissas!$C$12 -> 2 | I10: =I9*Premissas!$C$12 -> 2 | J10: =J9*Premissas!$C$12 -> 4 | ... Z10: =Z9*Premissas!$C$12 -> 4 | AA10: =SUM(C10:Z10) -> 74
B11: Clientes fechados via funil (novos) | C11: =ROUND(C10*Premissas!$C$13,0) -> 0 | D11: =ROUND(D10*Premissas!$C$13,0) -> 0 | E11: =ROUND(E10*Premissas!$C$13,0) -> 0 | F11: =ROUND(F10*Premissas!$C$13,0) -> 0 | G11: =ROUND(G10*Premissas!$C$13,0) -> 2 | H11: =ROUND(H10*Premissas!$C$13,0) -> 1 | I11: =ROUND(I10*Premissas!$C$13,0) -> 1 | J11: =ROUND(J10*Premissas!$C$13,0) -> 2 | ... Z11: =ROUND(Z10*Premissas!$C$13,0) -> 2 | AA11: =SUM(C11:Z11) -> 37
B12: Clientes-piloto convertidos em pagantes | C12: =IF(C5=Premissas!$C$26,Premissas!$C$25,0) -> 0 | D12: =IF(D5=Premissas!$C$26,Premissas!$C$25,0) -> 0 | E12: =IF(E5=Premissas!$C$26,Premissas!$C$25,0) -> 0 | F12: =IF(F5=Premissas!$C$26,Premissas!$C$25,0) -> 3 | G12: =IF(G5=Premissas!$C$26,Premissas!$C$25,0) -> 0 | H12: =IF(H5=Premissas!$C$26,Premissas!$C$25,0) -> 0 | I12: =IF(I5=Premissas!$C$26,Premissas!$C$25,0) -> 0 | J12: =IF(J5=Premissas!$C$26,Premissas!$C$25,0) -> 0 | ... Z12: =IF(Z5=Premissas!$C$26,Premissas!$C$25,0) -> 0 | AA12: =SUM(C12:Z12) -> 3
B13: Total de novos clientes pagantes no mês | C13: =C11+C12 -> 0 | D13: =D11+D12 -> 0 | E13: =E11+E12 -> 0 | F13: =F11+F12 -> 3 | G13: =G11+G12 -> 2 | H13: =H11+H12 -> 1 | I13: =I11+I12 -> 1 | J13: =J11+J12 -> 2 | ... Z13: =Z11+Z12 -> 2 | AA13: =SUM(C13:Z13) -> 40
B14: Clientes pagantes ativos (acumulado) | C14: =C13 -> 0 | D14: =C14+D13 -> 0 | E14: =D14+E13 -> 0 | F14: =E14+F13 -> 3 | G14: =F14+G13 -> 5 | H14: =G14+H13 -> 6 | I14: =H14+I13 -> 7 | J14: =I14+J13 -> 9 | K14: =J14+K13 -> 10 | ... Z14: =Y14+Z13 -> 40 | AA14: =Z14 -> 40
B16: Nota: 'Leads prospectados' é a única premissa de volume comercial inserida manualmente mês a mês — calibrada para reproduzir os marcos de clientes ativos citados na Seção 20 (3 no M3 · 6 no M6 · 10 no M9 · 16 no M12 · 28 no M18 · 40 no M24). Todas as demais linhas são fórmulas das taxas de conversão da aba Premissas.

Sheet Receita e Clientes
A1: Receita e Clientes — Mês a Mês
A2: MRR = Clientes ativos (aba Funil de Vendas) × Ticket médio (aba Premissas)
B4: Métrica | C4: M1 | D4: M2 | E4: M3 | F4: M4 | G4: M5 | H4: M6 | I4: M7 | J4: M8 | K4: M9 | L4: M10 | M4: M11 | N4: M12 | O4: M13 | P4: M14 | Q4: M15 | R4: M16 | S4: M17 | T4: M18 | U4: M19 | V4: M20 | W4: M21 | X4: M22 | Y4: M23 | Z4: M24 | AA4: Fim 24m
B5: Clientes pagantes ativos | C5: ='Funil de Vendas'!C14 -> 0 | D5: ='Funil de Vendas'!D14 -> 0 | E5: ='Funil de Vendas'!E14 -> 0 | F5: ='Funil de Vendas'!F14 -> 3 | G5: ='Funil de Vendas'!G14 -> 5 | H5: ='Funil de Vendas'!H14 -> 6 | I5: ='Funil de Vendas'!I14 -> 7 | J5: ='Funil de Vendas'!J14 -> 9 | ... Z5: ='Funil de Vendas'!Z14 -> 40 | AA5: =Z5 -> 40
B6: MRR — Receita Recorrente Mensal (R$) | C6: =C5*Premissas!$C$8 -> 0 | D6: =D5*Premissas!$C$8 -> 0 | E6: =E5*Premissas!$C$8 -> 0 | F6: =F5*Premissas!$C$8 -> 22500 | G6: =G5*Premissas!$C$8 -> 37500 | H6: =H5*Premissas!$C$8 -> 45000 | I6: =I5*Premissas!$C$8 -> 52500 | J6: =J5*Premissas!$C$8 -> 67500 | ... Z6: =Z5*Premissas!$C$8 -> 300000 | AA6: =Z6 -> 300000
B7: ARR — Receita Recorrente Anualizada (R$) | C7: =C6*12 -> 0 | D7: =D6*12 -> 0 | E7: =E6*12 -> 0 | F7: =F6*12 -> 270000 | G7: =G6*12 -> 450000 | H7: =H6*12 -> 540000 | I7: =I6*12 -> 630000 | J7: =J6*12 -> 810000 | ... Z7: =Z6*12 -> 3600000 | AA7: =Z7 -> 3600000
B9: CONFERÊNCIA COM A DOCUMENTAÇÃO (Seção 20)
B10: Marco | C10: Mês | D10: Clientes (doc.) | E10: Clientes (modelo) | F10: MRR (doc.) | G10: MRR (modelo) | H10: Confere?
B11: Fim do Piloto | C11: 3 | D11: 3 | E11: =Premissas!$C$25 -> 3 | F11: 0 | G11: =E6 -> 0 | H11: =IF(AND(D11=E11,F11=G11),"OK","Confira") -> OK
B12: — | C12: 6 | D12: 6 | E12: =H5 -> 6 | F12: 45000 | G12: =H6 -> 45000 | H12: =IF(AND(D12=E12,F12=G12),"OK","Confira") -> OK
B13: Meta Early Adopters | C13: 9 | D13: 10 | E13: =K5 -> 10 | F13: 75000 | G13: =K6 -> 75000 | H13: =IF(AND(D13=E13,F13=G13),"OK","Confira") -> OK
B14: Fim do Ano 1 | C14: 12 | D14: 16 | E14: =N5 -> 16 | F14: 120000 | G14: =N6 -> 120000 | H14: =IF(AND(D14=E14,F14=G14),"OK","Confira") -> OK
B15: — | C15: 18 | D15: 28 | E15: =T5 -> 28 | F15: 210000 | G15: =T6 -> 210000 | H15: =IF(AND(D15=E15,F15=G15),"OK","Confira") -> OK
B16: Meta Final (= SOM Seção 5) | C16: 24 | D16: 40 | E16: =Z5 -> 40 | F16: 300000 | G16: =Z6 -> 300000 | H16: =IF(AND(D16=E16,F16=G16),"OK","Confira") -> OK
B18: Nota sobre o Mês 3: os 3 clientes do piloto já existem nesse mês, mas ainda não pagam (R$0 MRR) — por isso não entram em 'Clientes pagantes ativos' até o Mês 4, quando o piloto termina e eles passam a ser cobrados.

Sheet Custos Mensais
A1: Custos Mensais
A2: Custo fixo por fase + CAC + processamento de IA + comissão de vendas — todos ligados à aba Premissas
B4: Métrica | C4: M1 | D4: M2 | E4: M3 | F4: M4 | G4: M5 | H4: M6 | I4: M7 | J4: M8 | K4: M9 | L4: M10 | M4: M11 | N4: M12 | O4: M13 | P4: M14 | Q4: M15 | R4: M16 | S4: M17 | T4: M18 | U4: M19 | V4: M20 | W4: M21 | X4: M22 | Y4: M23 | Z4: M24 | AA4: Total 24m
B5: Mês nº | C5: 1 | D5: 2 | E5: 3 | F5: 4 | G5: 5 | H5: 6 | I5: 7 | J5: 8 | K5: 9 | L5: 10 | M5: 11 | N5: 12 | O5: 13 | P5: 14 | Q5: 15 | R5: 16 | S5: 17 | T5: 18 | U5: 19 | V5: 20 | W5: 21 | X5: 22 | Y5: 23 | Z5: 24
B6: Custo fixo do mês (por fase) | C6: =IF(C5<=3,Premissas!$C$20,IF(C5<=9,Premissas!$C$21,IF(C5<=18,Premissas!$C$22,Premissas!$C$23))) -> 2500 | D6: =IF(D5<=3,Premissas!$C$20,IF(D5<=9,Premissas!$C$21,IF(D5<=18,Premissas!$C$22,Premissas!$C$23))) -> 2500 | E6: =IF(E5<=3,Premissas!$C$20,IF(E5<=9,Premissas!$C$21,IF(E5<=18,Premissas!$C$22,Premissas!$C$23))) -> 2500 | F6: =IF(F5<=3,Premissas!$C$20,IF(F5<=9,Premissas!$C$21,IF(F5<=18,Premissas!$C$22,Premissas!$C$23))) -> 7000 | G6: =IF(G5<=3,Premissas!$C$20,IF(G5<=9,Premissas!$C$21,IF(G5<=18,Premissas!$C$22,Premissas!$C$23))) -> 7000 | H6: =IF(H5<=3,Premissas!$C$20,IF(H5<=9,Premissas!$C$21,IF(H5<=18,Premissas!$C$22,Premissas!$C$23))) -> 7000 | I6: =IF(I5<=3,Premissas!$C$20,IF(I5<=9,Premissas!$C$21,IF(I5<=18,Premissas!$C$22,Premissas!$C$23))) -> 7000 | J6: =IF(J5<=3,Premissas!$C$20,IF(J5<=9,Premissas!$C$21,IF(J5<=18,Premissas!$C$22,Premissas!$C$23))) -> 7000 | ... Z6: =IF(Z5<=3,Premissas!$C$20,IF(Z5<=9,Premissas!$C$21,IF(Z5<=18,Premissas!$C$22,Premissas!$C$23))) -> 19000 | AA6: =SUM(C6:Z6) -> 289500
B7: Novos clientes via funil (ref.) | C7: ='Funil de Vendas'!C11 -> 0 | D7: ='Funil de Vendas'!D11 -> 0 | E7: ='Funil de Vendas'!E11 -> 0 | F7: ='Funil de Vendas'!F11 -> 0 | G7: ='Funil de Vendas'!G11 -> 2 | H7: ='Funil de Vendas'!H11 -> 1 | I7: ='Funil de Vendas'!I11 -> 1 | J7: ='Funil de Vendas'!J11 -> 2 | ... Z7: ='Funil de Vendas'!Z11 -> 2 | AA7: =SUM(C7:Z7) -> 37
B8: CAC total do mês | C8: =C7*Premissas!$C$16 -> 0 | D8: =D7*Premissas!$C$16 -> 0 | E8: =E7*Premissas!$C$16 -> 0 | F8: =F7*Premissas!$C$16 -> 0 | G8: =G7*Premissas!$C$16 -> 6000 | H8: =H7*Premissas!$C$16 -> 3000 | I8: =I7*Premissas!$C$16 -> 3000 | J8: =J7*Premissas!$C$16 -> 6000 | ... Z8: =Z7*Premissas!$C$16 -> 6000 | AA8: =SUM(C8:Z8) -> 111000
B9: Colaboradores cobertos (total ativo) | C9: ='Receita e Clientes'!C5*Premissas!$C$6 -> 0 | D9: ='Receita e Clientes'!D5*Premissas!$C$6 -> 0 | E9: ='Receita e Clientes'!E5*Premissas!$C$6 -> 0 | F9: ='Receita e Clientes'!F5*Premissas!$C$6 -> 900 | G9: ='Receita e Clientes'!G5*Premissas!$C$6 -> 1500 | H9: ='Receita e Clientes'!H5*Premissas!$C$6 -> 1800 | I9: ='Receita e Clientes'!I5*Premissas!$C$6 -> 2100 | J9: ='Receita e Clientes'!J5*Premissas!$C$6 -> 2700 | ... Z9: ='Receita e Clientes'!Z5*Premissas!$C$6 -> 12000 | AA9: =Z9 -> 12000
B10: Custo de processamento de IA | C10: =C9*Premissas!$C$17 -> 0 | D10: =D9*Premissas!$C$17 -> 0 | E10: =E9*Premissas!$C$17 -> 0 | F10: =F9*Premissas!$C$17 -> 450 | G10: =G9*Premissas!$C$17 -> 750 | H10: =H9*Premissas!$C$17 -> 900 | I10: =I9*Premissas!$C$17 -> 1050 | J10: =J9*Premissas!$C$17 -> 1350 | ... Z10: =Z9*Premissas!$C$17 -> 6000 | AA10: =SUM(C10:Z10) -> 64500
B11: Comissão de vendas (% do MRR) | C11: ='Receita e Clientes'!C6*Premissas!$C$18 -> 0 | D11: ='Receita e Clientes'!D6*Premissas!$C$18 -> 0 | E11: ='Receita e Clientes'!E6*Premissas!$C$18 -> 0 | F11: ='Receita e Clientes'!F6*Premissas!$C$18 -> 1125 | G11: ='Receita e Clientes'!G6*Premissas!$C$18 -> 1875 | H11: ='Receita e Clientes'!H6*Premissas!$C$18 -> 2250 | I11: ='Receita e Clientes'!I6*Premissas!$C$18 -> 2625 | J11: ='Receita e Clientes'!J6*Premissas!$C$18 -> 3375 | ... Z11: ='Receita e Clientes'!Z6*Premissas!$C$18 -> 15000 | AA11: =SUM(C11:Z11) -> 161250
B12: CUSTO TOTAL DO MÊS | C12: =C6+C8+C10+C11 -> 2500 | D12: =D6+D8+D10+D11 -> 2500 | E12: =E6+E8+E10+E11 -> 2500 | F12: =F6+F8+F10+F11 -> 8575 | G12: =G6+G8+G10+G11 -> 15625 | H12: =H6+H8+H10+H11 -> 13150 | I12: =I6+I8+I10+I11 -> 13675 | J12: =J6+J8+J10+J11 -> 17725 | ... Z12: =Z6+Z8+Z10+Z11 -> 46000 | AA12: =SUM(C12:Z12) -> 626250

Sheet DRE Mensal
A1: DRE Mensal e Caixa Acumulado
A2: Resultado = Receita − Custo · Caixa acumulado mostra o mês exato do break-even
B4: Métrica | C4: M1 | D4: M2 | E4: M3 | F4: M4 | G4: M5 | H4: M6 | I4: M7 | J4: M8 | K4: M9 | L4: M10 | M4: M11 | N4: M12 | O4: M13 | P4: M14 | Q4: M15 | R4: M16 | S4: M17 | T4: M18 | U4: M19 | V4: M20 | W4: M21 | X4: M22 | Y4: M23 | Z4: M24 | AA4: Total 24m
B5: Receita (MRR) | C5: ='Receita e Clientes'!C6 -> 0 | D5: ='Receita e Clientes'!D6 -> 0 | E5: ='Receita e Clientes'!E6 -> 0 | F5: ='Receita e Clientes'!F6 -> 22500 | G5: ='Receita e Clientes'!G6 -> 37500 | H5: ='Receita e Clientes'!H6 -> 45000 | I5: ='Receita e Clientes'!I6 -> 52500 | J5: ='Receita e Clientes'!J6 -> 67500 | ... Z5: ='Receita e Clientes'!Z6 -> 300000 | AA5: =SUM(C5:Z5) -> 3225000
B6: Custo total | C6: ='Custos Mensais'!C12 -> 2500 | D6: ='Custos Mensais'!D12 -> 2500 | E6: ='Custos Mensais'!E12 -> 2500 | F6: ='Custos Mensais'!F12 -> 8575 | G6: ='Custos Mensais'!G12 -> 15625 | H6: ='Custos Mensais'!H12 -> 13150 | I6: ='Custos Mensais'!I12 -> 13675 | J6: ='Custos Mensais'!J12 -> 17725 | ... Z6: ='Custos Mensais'!Z12 -> 46000 | AA6: =SUM(C6:Z6) -> 626250
B7: Resultado operacional do mês | C7: =C5-C6 -> -2500 | D7: =D5-D6 -> -2500 | E7: =E5-E6 -> -2500 | F7: =F5-F6 -> 13925 | G7: =G5-G6 -> 21875 | H7: =H5-H6 -> 31850 | I7: =I5-I6 -> 38825 | J7: =J5-J6 -> 49775 | ... Z7: =Z5-Z6 -> 254000 | AA7: =SUM(C7:Z7) -> 2598750
B8: Caixa acumulado (desde M1) | C8: =C7 -> -2500 | D8: =C8+D7 -> -5000 | E8: =D8+E7 -> -7500 | F8: =E8+F7 -> 6425 | G8: =F8+G7 -> 28300 | H8: =G8+H7 -> 60150 | I8: =H8+I7 -> 98975 | J8: =I8+J7 -> 148750 | K8: =J8+K7 -> 208500 | ... Z8: =Y8+Z7 -> 2598750 | AA8: =Z8 -> 2598750
B10: Capital mínimo necessário até o break-even | E10: =-MIN(C8:Z8) -> 7500 | F10: (= pior caixa acumulado, em módulo — o quanto a operação precisa de aporte/caixa próprio até virar positiva)
B11: Mês do break-even (1º mês com caixa acumulado ≥ 0) | E11: =IFERROR(MATCH(TRUE(),INDEX(C8:Z8>=0,0),0),"Não atingido em 24 meses") -> 4 | F11: (fórmula de matriz simples via INDEX/MATCH — primeiro mês em que o caixa acumulado deixa de ser negativo)

Sheet Resumo Anual
A1: Resumo Anual — Ano 1 × Ano 2 × Total 24 Meses
A2: Mesmo formato da Seção 20 da documentação — valores recalculados por SUMIFS a partir da DRE Mensal
B4: Período | C4: Receita | D4: Custos | E4: Resultado Operacional
B5: Ano 1 (M1–M12) | C5: =SUM('DRE Mensal'!C5:N5) -> 615000 | D5: =SUM('DRE Mensal'!C6:N6) -> 173550 | E5: =C5-D5 -> 441450
B6: Ano 2 (M13–M24) | C6: =SUM('DRE Mensal'!O5:Z5) -> 2610000 | D6: =SUM('DRE Mensal'!O6:Z6) -> 452700 | E6: =C6-D6 -> 2157300
B7: Total 24 meses | C7: =SUM('DRE Mensal'!C5:Z5) -> 3225000 | D7: =SUM('DRE Mensal'!C6:Z6) -> 626250 | E7: =C7-D7 -> 2598750
B9: Indicadores-Chave
B10: Indicador | C10: Valor | G10: Nota
B11: ARR ao final de 24 meses | C11: ='Receita e Clientes'!Z7 -> 3600000 | G11: MRR do mês 24 × 12 — compare com a meta de R$3,6 milhões (SOM, Seção 5).
B12: Capital mínimo necessário até o break-even | C12: ='DRE Mensal'!E10 -> 7500 | G12: Pior caixa acumulado em módulo — compare com os ~R$45 mil citados na Seção 20.
B13: Mês do break-even | C13: ='DRE Mensal'!E11 -> 4 | G13: Primeiro mês com caixa acumulado ≥ 0 — compare com o Mês 6 citado na Seção 20.
B14: Clientes ativos ao final de 24 meses | C14: ='Receita e Clientes'!Z5 -> 40 | G14: Compare com os 40 clientes do SOM (Seção 5).

Sheet Funil Padrão (Seção 19)
A1: Funil de Vendas em Regime de Maturidade
A2: Mesma tabela da Seção 19 da documentação — recalculada a partir das taxas de conversão da aba Premissas
B4: Etapa | C4: Volume mensal (meta) | D4: Conversão p/ próxima etapa
B5: 1. Leads prospectados (outbound + LinkedIn) | C5: 100 | D5: =Premissas!$C$10 -> 0.2
B6: 2. Leads qualificados (SQL) | C6: =ROUND(C5*D5,0) -> 20 | D6: =Premissas!$C$11 -> 0.4
B7: 3. Diagnóstico / Demo agendada | C7: =ROUND(C6*D6,0) -> 8 | D7: =Premissas!$C$12 -> 0.5
B8: 4. Proposta enviada | C8: =ROUND(C7*D7,0) -> 4 | D8: =Premissas!$C$13 -> 0.5
B9: 5. Cliente fechado | C9: =ROUND(C8*D8,0) -> 2 | D9: —
B11: Conversão geral (Lead → Cliente fechado) | C11: =C9/C5 -> 0.02
B13: Metas por Fase (Seção 19)
B14: Fase | C14: Período | D14: Meta
B15: Fase 1 · Piloto | C15: M1–M3 | D15: =Premissas!C25&" empresas parceiras, sem cobrança" -> 3 empresas parceiras, sem cobrança
B16: Fase 2 · Early Adopters | C16: M4–M9 | D16: ="Meta de 10 clientes pagantes (veja mês 9 na aba Receita e Clientes)" -> Meta de 10 clientes pagantes (veja mês 9 na aba Receita e Clientes)
B17: Fase 3 · Scale | C17: M10–M24 | D17: ="Meta acumulada de "&Premissas!C28&" clientes (= SOM, Seção 5)" -> Meta acumulada de 40 clientes (= SOM, Seção 5)

Sheet Comparáveis de Mercado
A1: Comparáveis Reais do Setor
A2: Empresas reais usadas para calibrar as metas do modelo (Seção 20 da documentação) — dados reportados publicamente, não fictícios
B4: Empresa | C4: Modelo | D4: Marco real reportado | E4: Fonte
B5: Scaleup | C5: Capacitação empreendedora (B2C, alto volume) | D5: R$3 milhões de faturamento já no 1º ano | E5: Baguete
B6: Witseed | C6: Educação corporativa B2B (HRAcademy) | D6: Aporte seed de R$920 mil após ~4 anos; equipe de 15 para 27 pessoas | E6: Baguete
B7: Education Journey | C7: Curadoria de trilhas p/ empresas — modelo mais próximo do SkillWay | D7: Contrato fechado com a Ambev (4 mil cursos) ainda em estágio inicial | E7: Forbes Brasil
B8: Gupy | C8: HRTech (recrutamento → hoje suíte completa) | D8: 15% de crescimento médio mensal de receita até a Series A, já com "centenas" de clientes pagantes | E8: LAVCA
B9: Sólides | C9: RH comportamental p/ PME (concorrente, Seção 3) | D9: 45 mil clientes, mas via aporte de R$530 milhões + aquisições — não crescimento orgânico | E9: Seção 3 da documentação
B11: Benchmarks complementares de SaaS B2B no Brasil
B12: MRR mediano pré-seed | C12: ~R$15.000/mês
B13: CAC — segmento PME | C13: R$3.000 a R$15.000 por cliente
B14: CAC — segmento mid-market | C14: R$30.000 a R$150.000 por cliente
B15: LTV/CAC saudável | C15: ≥ 3x
B16: Churn mensal — estágio pré-seed | C16: ~7,5%
B17: Churn mensal — estágio Series B+ | C17: ~1%
B18: Fonte | C18: Baita, Metrikia, BeansTech (citados na Seção 20 da documentação)
B20: Como este modelo usa esses benchmarks: o CAC de R$3.000/cliente (aba Premissas) está no piso da faixa PME; o ritmo de fechamento (2 clientes/mês em regime de maturidade) é mais conservador que o da Gupy; e o preço médio de R$25/colaborador/mês está abaixo do que HRTechs consolidadas cobram, coerente com uma empresa em estágio inicial.
