Workbook

Sheet Leia-me
B2: SkillWay — Planejamento Financeiro (versão 2)
B3: Habilidades que abrem caminhos · Empreendedorismo · Gestão de TI · IFSP Catanduva
B5: Esta planilha segue o roteiro da aula de Planejamento Financeiro (Profª Drª Vanise R. Z. Ralio): investimento → custos → preço → DRE → fluxo de caixa → indicadores. Os números são fictícios, mas calibrados em empresas reais do setor (aba Comparáveis). Mude qualquer valor azul na aba Premissas e tudo recalcula.
B7: Aba | C7: Slide da aula | D7: O que mostra
B8: Painel | C8: — | D8: Resumo do cenário ativo e os 8 gráficos do plano.
B9: Premissas | C9: 4 (projeção de vendas) | D9: Todas as entradas, com fonte. Seletor de cenário.
B10: Investimento Inicial | C10: 5 e 6 | D10: Pré-operacionais + fixos + capital de giro; origem dos recursos; depreciação.
B11: Funil de Vendas | C11: 4 | D11: Leads → clientes, mês a mês.
B12: Receita e Clientes | C12: 4 | D12: Clientes, colaboradores atendidos, MRR e ARR; conferência com a documentação.
B13: Custos Fixos | C13: 7 | D13: Tabela do slide por fase, equipe CLT e projeção mensal.
B14: Custos Variáveis | C14: 8 | D14: Ficha técnica por cliente e por colaborador e projeção mensal.
B15: Custo Unitário e Preço | C15: 9 | D15: Custo unitário (MDO + MP + fixo) e preço calculado com impostos e lucro.
B16: Tributação | C16: 11 (DAS) | D16: Simples Nacional: RBT12, alíquota efetiva e simulação do Fator R.
B17: DRE Mensal | C17: 10 e 11 | D17: Resultado mês a mês em regime de competência.
B18: DRE Anual | C18: 11 | D18: O quadro do slide com R$ e %, Ano 1 × Ano 2.
... B23: Comparáveis | C23: — | D23: Empresas reais usadas como referência.
B25: Cores
B26: Texto azul: premissa que você pode mudar
B27: Texto preto: fórmula
B28: Texto verde: valor puxado de outra aba
B29: Fundo amarelo: alavanca principal
B30: Fundo lilás: resultado-chave
B32: O que mudou em relação à versão anterior
B33: Item | C33: Versão anterior (Seção 20) | D33: Agora | E33: Por quê
B34: Receita em 24 meses | C34: mesma base | D34: =Indicadores!E8 -> 3225000 | E34: Funil, preço e marcos de clientes foram mantidos (cenário Base).
B35: Resultado do Ano 1 | C35: 441450 | D35: =Indicadores!C9 -> 328990.73 | E35: Antes era o resultado sem impostos. Agora entram DAS, inadimplência, tarifas, depreciação, despesas pré-operacionais e rendimentos.
B36: Investimento inicial | C36: 7500 | D36: =Indicadores!C7 -> 25840 | E36: Antes só os 3 meses de custo fixo. Agora segue o slide 6: pré-operacionais + fixos + capital de giro + reserva para vendas a prazo.
B37: Primeiro mês positivo | C37: 4 | D37: =Indicadores!C20 -> 4 | E37: Continua logo após o piloto.
B38: Impostos | C38: não calculados | D38: ='DRE Anual'!G9 -> 610512.2 | E38: Simples Nacional, Anexo V, com alíquota efetiva pela RBT12 (aba Tributação).
B39: Fluxo de caixa | C39: não havia | D39: =Indicadores!C22 -> 875.34565 | E39: Agora em regime de caixa, com prazos de recebimento e pagamento. Valor ao lado: menor saldo do período.

Sheet Painel
B2: SkillWay — Painel do plano financeiro
B3: Resumo do cenário ativo. Todos os números vêm das outras abas.
B5: Cenário ativo | E5: Investimento inicial | H5: Receita em 24 meses
B6: =CHOOSE(Premissas!$C$7,"Pessimista","Base","Otimista") -> Base | E6: =Indicadores!C7 -> 25840 | H6: =Indicadores!E8 -> 3225000
B8: Lucro líquido — Ano 1 | E8: Lucro líquido — Ano 2 | H8: Margem de contribuição (24m)
B9: =Indicadores!C9 -> 328990.73 | E9: =Indicadores!D9 -> 1703065.9 | H9: =Indicadores!E15 -> 0.72987529
B11: Ponto de equilíbrio — 1º mês positivo | E11: Retorno do investimento | H11: Clientes ativos no M24
B12: =Indicadores!C20 -> 4 | E12: =Indicadores!C12 -> 7 | H12: ='Receita e Clientes'!AA11 -> 40
P71: Dados: composição dos gastos — Ano 2
P72: Processamento de IA | Q72: ='DRE Mensal'!AC9 -> 52200
P73: DAS (impostos) | Q73: ='DRE Mensal'!AC10 -> 507610.86
P74: Comissões e tarifas | Q74: ='DRE Mensal'!AC11 -> 131544
P75: Inadimplência | Q75: ='DRE Mensal'!AC12 -> 26100
P76: Mão de obra | Q76: ='DRE Mensal'!AC16 -> 101400
P77: Demais custos fixos | Q77: ='DRE Mensal'!AC17 -> 96600
P78: Aquisição de clientes | Q78: ='DRE Mensal'!AC18 -> 72000
P79: Depreciação | Q79: ='DRE Mensal'!AC19 -> 1220

Sheet Premissas
B2: Premissas do modelo
B3: Todas as entradas em um só lugar. Texto azul = premissa editável · fundo amarelo = alavanca principal · as demais abas são fórmulas.
B5: Premissa | C5: Valor | D5: Unidade | E5: Fonte / justificativa
B6: CENÁRIO ATIVO
B7: Cenário (1 = Pessimista · 2 = Base · 3 = Otimista) | C7: 2 | D7: seletor | E7: Troque para 1 ou 3 e todo o arquivo recalcula. A aba Cenários guarda a foto dos três resultados.
B8: Alavancas por cenário | F8: Pessimista | G8: Base | H8: Otimista
B9: Multiplicador de leads prospectados | C9: =INDEX(F9:H9,Premissas!$C$7) -> 1 | D9: x | E9: Pessimista: prospecção 40% abaixo do planejado; otimista: 30% acima. | F9: 0.6 | G9: 1 | H9: 1.3
B10: Multiplicador do preço médio | C10: =INDEX(F10:H10,Premissas!$C$7) -> 1 | D10: x | E10: Pessimista: desconto médio de 8% para fechar contratos. | F10: 0.92 | G10: 1 | H10: 1
B11: Cancelamento mensal a partir da renovação (M13+) | C11: =INDEX(F11:H11,Premissas!$C$7) -> 0 | D11: % a.m. | E11: Contratos anuais: só há saída na renovação. Base 0% (meta do plano); pessimista 2% a.m. no Ano 2 (mediana pré-seed BR é 7,5%, mas medida sobre PME com contrato mensal). | F11: 0.02 | G11: 0 | H11: 0
B12: Multiplicador do CAC | C12: =INDEX(F12:H12,Premissas!$C$7) -> 1 | D12: x | E12: Pessimista: aquisição 30% mais cara. | F12: 1.3 | G12: 1 | H12: 0.9
B13: PRODUTO E PREÇO (Seção 19 da documentação)
B14: Colaboradores médios por cliente | C14: 300 | D14: colaboradores | E14: Média entre os planos (Starter 100–300, Growth 301–800, Enterprise 801–2.000), ponderada pelo perfil de cliente-alvo.
B15: Preço médio por colaborador/mês (cenário base) | C15: 25 | D15: R$/colab/mês | E15: Média ponderada de Starter R$29, Growth R$24 e Enterprise R$19 — o mesmo R$25 usado no SOM (Seção 5).
B16: Preço médio aplicado no cenário | C16: =Premissas!$C$15*Premissas!$C$10 -> 25 | D16: R$/colab/mês | E16: Fórmula: preço base × multiplicador do cenário.
B17: Ticket médio mensal por cliente (ARPA) | C17: =Premissas!$C$14*Premissas!$C$16 -> 7500 | D17: R$/cliente/mês | E17: Colaboradores médios × preço por colaborador.
B18: Preço do plano Starter | C18: 29 | D18: R$/colab/mês | E18: Tabela de planos do sistema (js/catalog.js) e Seção 19.
B19: Preço do plano Growth | C19: 24 | D19: R$/colab/mês | E19: Idem.
B20: Preço do plano Enterprise | C20: 19 | D20: R$/colab/mês | E20: Idem.
B21: FUNIL DE VENDAS (Seção 19)
B22: Lead → lead qualificado | C22: 0.2 | D22: % | E22: Referência de outbound B2B para PME.
B23: Qualificado → demonstração | C23: 0.4 | D23: % | E23: Idem.
B24: Demonstração → proposta | C24: 0.5 | D24: % | E24: Idem.
B25: Proposta → cliente fechado | C25: 0.5 | D25: % | E25: Idem.
B26: Conversão geral (lead → cliente) | C26: =Premissas!$C$22*Premissas!$C$23*Premissas!$C$24*Premissas!$C$25 -> 0.02 | D26: % | E26: 100 leads/mês = 2 clientes/mês, como na Seção 19.
B27: PILOTO E FASES
B28: Clientes-piloto (sem cobrança) | C28: 3 | D28: clientes | E28: Piloto com 2 a 3 empresas parceiras (Seção 19); adotado 3.
B29: Mês em que o piloto vira cliente pagante | C29: 4 | D29: mês | E29: Piloto roda do M1 ao M3.
B30: Último mês da Fase 1 · Piloto | C30: 3 | D30: mês | E30: Fases da Seção 19.
B31: Último mês da Fase 2 · Early adopters | C31: 9 | D31: mês | E31: Idem.
B32: Último mês da Fase 3a · Scale inicial | C32: 18 | D32: mês | E32: A partir do mês seguinte: Fase 3b · Scale maduro.
B33: Primeiro mês em que pode haver cancelamento | C33: 13 | D33: mês | E33: Renovação dos contratos anuais.
B34: CUSTOS VARIÁVEIS E DE AQUISIÇÃO
B35: CAC por cliente novo vindo do funil | C35: 3000 | D35: R$/cliente | E35: Piso da faixa PME (R$3–15 mil) dos benchmarks de SaaS B2B brasileiro. Clientes-piloto não têm CAC.
B36: CAC aplicado no cenário | C36: =Premissas!$C$35*Premissas!$C$12 -> 3000 | D36: R$/cliente | E36: CAC base × multiplicador do cenário.
B37: Processamento de IA por colaborador atendido/mês | C37: 0.5 | D37: R$/colab/mês | E37: Chamadas à API do Claude (diagnóstico, leitura de perfil, mentor) + banco. Inclui os clientes-piloto, que usam sem pagar.
B38: Comissão de vendas sobre a receita | C38: 0.05 | D38: % da receita | E38: Paga no mês seguinte ao da receita.
B39: Tarifa de cobrança por fatura (boleto/Pix) | C39: 3 | D39: R$/cliente/mês | E39: Uma fatura por cliente por mês (cobrança B2B, sem cartão).
B40: Inadimplência (perda sobre a receita) | C40: 0.01 | D40: % da receita | E40: Parte da receita faturada que não é recebida.
B41: PRAZOS E FINANÇAS
B42: Prazo de recebimento das faturas | C42: 30 dias | D42: estrutura | E42: Fatura emitida no mês, vencimento em 30 dias: a receita de março entra no caixa em abril (slide 12). Salários, DAS e comissões também são pagos no mês seguinte. É a estrutura das fórmulas do Fluxo de Caixa, não uma alavanca.
B43: Tarifas bancárias (conta PJ) | C43: 60 | D43: R$/mês | E43: Pacote de conta PJ com emissão de boletos.
B44: Rendimento líquido do caixa aplicado | C44: 0.008 | D44: % a.m. | E44: Estimativa conservadora para CDB/Tesouro com liquidez diária, já descontado o IR. Confira a taxa do momento.
B45: Encargos e provisões sobre salários (CLT) | C45: 0.3 | D45: % do salário | E45: FGTS 8% + 13º + férias e 1/3 + FGTS sobre provisões. A contribuição patronal ao INSS já está dentro do DAS (Simples).
B46: IMPOSTOS (Simples Nacional — aba Tributação)
B47: Fator R mínimo para o Anexo III | C47: 0.28 | D47: % | E47: LC 123/2006 e Resolução CGSN 140/2018: folha de 12 meses ÷ receita de 12 meses ≥ 28% → Anexo III; abaixo → Anexo V.
B48: Número de sócios | C48: 4 | D48: pessoas | E48: Equipe fundadora do projeto.
B49: Teto do INSS 2026 | C49: 8475.55 | D49: R$/mês | E49: Contribuição do sócio sobre pró-labore: 11% até o teto.
B50: INSS do sócio sobre pró-labore | C50: 0.11 | D50: % | E50: Contribuinte individual com retenção pela empresa.
B51: INVESTIMENTO E DEPRECIAÇÃO
B52: Meses de custo fixo no capital de giro | C52: 3 | D52: meses | E52: Slide 6: capital de giro de 3 a 6 meses. Adotado 3: a receita começa no M4.
B53: Meses de custo da Fase 2 reservados para vendas a prazo | C53: 1 | D53: meses | E53: Cobre o primeiro mês de faturamento, que só entra no caixa no mês seguinte.
B54: Vida útil de máquinas e equipamentos | C54: 60 | D54: meses | E54: Computadores: 20% ao ano (5 anos).
B55: Vida útil de serviços de implantação (intangível) | C55: 60 | D55: meses | E55: Amortização em 5 anos.
B56: META (Seção 5 — SOM)
B57: Clientes ativos ao fim de 24 meses | C57: 40 | D57: clientes | E57: SOM: 40 empresas em São Paulo.
B58: Vida média estimada de um cliente (para o LTV) | C58: 36 | D58: meses | E58: Contrato anual renovado em média 3 vezes.
B59: Lucro desejado na formação do preço | C59: 0.2 | D59: % do preço | E59: Usado na aba Custo Unitário e Preço (fórmula do slide 9).

Sheet Investimento Inicial
B2: Necessidade de investimentos
B3: Modelo do slide 6: despesas pré-operacionais + investimentos fixos + capital de giro.
B5: Descrição | C5: R$ total | D5: % do total | E5: Observação
B6: 1 - Despesas pré-operacionais
B7: Gastos com pesquisa de mercado | C7: 500 | E7: Questionário de validação (22 respostas) e entrevistas: impulsionamento e brindes.
B8: Marca / empresa / publicidade | C8: 1500 | E8: Identidade visual, site institucional e material de lançamento.
B9: Registro da marca (INPI) | C9: 440 | E9: Pedido + concessão com desconto para ME. Conferir a tabela de retribuições vigente do INPI.
B10: Projeto técnico (contrato SaaS, termos de uso e LGPD) | C10: 2000 | E10: No lugar de "engenheiro/projeto técnico": assessoria jurídica para contrato e privacidade de dados.
B11: Registro, alvarás e licenças | C11: 800 | E11: Abertura na Junta Comercial de SP, alvará municipal e certificado digital e-CNPJ.
B12: Subtotal 1 | C12: =SUM(C7:C11) -> 5240 | D12: =C12/$C$31 -> 0.20278638
B13: 2 - Investimentos fixos
B14: Instalações (construção, reforma) | C14: 0 | E14: Operação remota e em coworking: não há reforma.
B15: Máquinas e equipamentos | C15: 5500 | E15: Notebook para demonstrações e suporte, monitor e headset. Os sócios usam os próprios computadores.
B16: Móveis e utensílios | C16: 0 | E16: Incluídos no coworking.
B17: Serviços — implantação da plataforma (domínio, e-mail, ambiente de produção) | C17: 600 | E17: O MVP é desenvolvido pela equipe; aqui entra só a configuração do ambiente.
B18: Veículos | C18: 0 | E18: Não há.
B19: Subtotal 2 | C19: =SUM(C14:C18) -> 6100 | D19: =C19/$C$31 -> 0.23606811
B20: 3 - Capital de giro (3 a 6 meses)
B21: Estoque de materiais diretos | C21: 0 | E21: SaaS: não há estoque.
B22: Custo fixo inicial
B23: Água, luz, internet | C23: =('Custos Fixos'!$C$14+'Custos Fixos'!$C$15+'Custos Fixos'!$C$16)*Premissas!$C$52 -> 450 | E23: Custo da Fase 1 × meses de capital de giro.
B24: Aluguel, condomínio | C24: =('Custos Fixos'!$C$12+'Custos Fixos'!$C$13)*Premissas!$C$52 -> 0 | E24: Idem.
B25: Limpeza e conservação | C25: =('Custos Fixos'!$C$18)*Premissas!$C$52 -> 0 | E25: Idem.
B26: Seguros | C26: =('Custos Fixos'!$C$23)*Premissas!$C$52 -> 0 | E26: Idem.
B27: Mão de obra indireta com encargos | C27: ='Custos Fixos'!$C$29*Premissas!$C$52 -> 0 | E27: Idem (sem contratados na Fase 1).
B28: Outros (nuvem, ferramentas, contabilidade, marketing...) | C28: =('Custos Fixos'!$C$17+'Custos Fixos'!$C$19+'Custos Fixos'!$C$20+'Custos Fixos'!$C$21+'Custos Fixos'!$C$22+'Custos Fixos'!$C$24+'Custos Fixos'!$C$25+'Custos Fixos'!$C$26+'Custos Fixos'!$C$27)*Premissas!$C$52 -> 7050 | E28: Idem.
B29: Reserva de capital para suporte de vendas a prazo | C29: ='Custos Fixos'!$D$30*Premissas!$C$53 -> 7000 | E29: Um mês de custo da Fase 2: a primeira receita (M4) só entra no caixa no M5.
B30: Subtotal 3 | C30: =SUM(C21:C29) -> 14500 | D30: =C30/$C$31 -> 0.56114551
B31: TOTAL (1 + 2 + 3) | C31: =C12+C19+C30 -> 25840 | D31: =C31/$C$31 -> 1
B33: Origem dos recursos
B34: Recursos próprios (aporte dos sócios) — % | C34: 1 | E34: Slide 5: capital próprio ou de terceiros. Com investimento baixo, o plano é 100% próprio, sem juros.
B35: Aporte dos sócios | C35: =C31*C34 -> 25840
B36: Recursos de terceiros | C36: =C31-C35 -> 0 | E36: Se usar terceiros, inclua os juros no Resultado financeiro da DRE.
B37: Aporte por sócio | C37: =C35/Premissas!$C$48 -> 6460
B39: Depreciação + amortização mensal (vai para a DRE) | C39: =C15/Premissas!$C$54+(C17+C14+C16)/Premissas!$C$55+C18/Premissas!$C$54 -> 101.66667 | E39: Equipamentos ÷ vida útil + implantação ÷ prazo de amortização. Despesas pré-operacionais vão direto para a DRE do M1.

Sheet Funil de Vendas
B2: Funil de vendas mês a mês
B3: Leads prospectados (azul) é a única entrada de volume; o resto são as taxas da aba Premissas.
B5: Etapa | D5: M1 | E5: M2 | F5: M3 | G5: M4 | H5: M5 | I5: M6 | J5: M7 | K5: M8 | L5: M9 | M5: M10 | N5: M11 | O5: M12 | P5: M13 | Q5: M14 | R5: M15 | S5: M16 | T5: M17 | U5: M18 | V5: M19 | W5: M20 | X5: M21 | Y5: M22 | Z5: M23 | AA5: M24 | AB5: Ano 1 | AC5: Ano 2 | AD5: Total 24m
B6: Nº do mês | C6: 0 | D6: 1 | E6: 2 | F6: 3 | G6: 4 | H6: 5 | I6: 6 | J6: 7 | K6: 8 | L6: 9 | M6: 10 | N6: 11 | O6: 12 | P6: 13 | Q6: 14 | R6: 15 | S6: 16 | T6: 17 | U6: 18 | V6: 19 | W6: 20 | X6: 21 | Y6: 22 | Z6: 23 | AA6: 24
B7: Leads prospectados — plano base (entrada) | D7: 0 | E7: 0 | F7: 0 | G7: 0 | H7: 100 | I7: 50 | J7: 50 | K7: 100 | L7: 50 | M7: 100 | N7: 100 | O7: 100 | P7: 100 | Q7: 100 | R7: 100 | S7: 100 | T7: 100 | U7: 100 | V7: 100 | W7: 100 | X7: 100 | Y7: 100 | Z7: 100 | AA7: 100 | AB7: =SUM(D7:O7) -> 650 | AC7: =SUM(P7:AA7) -> 1200 | AD7: =SUM(D7:AA7) -> 1850
B8: Leads no cenário ativo | D8: =D7*Premissas!$C$9 -> 0 | E8: =E7*Premissas!$C$9 -> 0 | F8: =F7*Premissas!$C$9 -> 0 | G8: =G7*Premissas!$C$9 -> 0 | H8: =H7*Premissas!$C$9 -> 100 | I8: =I7*Premissas!$C$9 -> 50 | J8: =J7*Premissas!$C$9 -> 50 | K8: =K7*Premissas!$C$9 -> 100 | ... AA8: =AA7*Premissas!$C$9 -> 100 | AB8: =SUM(D8:O8) -> 650 | AC8: =SUM(P8:AA8) -> 1200 | AD8: =SUM(D8:AA8) -> 1850
B9: Leads qualificados | D9: =D8*Premissas!$C$22 -> 0 | E9: =E8*Premissas!$C$22 -> 0 | F9: =F8*Premissas!$C$22 -> 0 | G9: =G8*Premissas!$C$22 -> 0 | H9: =H8*Premissas!$C$22 -> 20 | I9: =I8*Premissas!$C$22 -> 10 | J9: =J8*Premissas!$C$22 -> 10 | K9: =K8*Premissas!$C$22 -> 20 | ... AA9: =AA8*Premissas!$C$22 -> 20 | AB9: =SUM(D9:O9) -> 130 | AC9: =SUM(P9:AA9) -> 240 | AD9: =SUM(D9:AA9) -> 370
B10: Demonstrações | D10: =D9*Premissas!$C$23 -> 0 | E10: =E9*Premissas!$C$23 -> 0 | F10: =F9*Premissas!$C$23 -> 0 | G10: =G9*Premissas!$C$23 -> 0 | H10: =H9*Premissas!$C$23 -> 8 | I10: =I9*Premissas!$C$23 -> 4 | J10: =J9*Premissas!$C$23 -> 4 | K10: =K9*Premissas!$C$23 -> 8 | ... AA10: =AA9*Premissas!$C$23 -> 8 | AB10: =SUM(D10:O10) -> 52 | AC10: =SUM(P10:AA10) -> 96 | AD10: =SUM(D10:AA10) -> 148
B11: Propostas enviadas | D11: =D10*Premissas!$C$24 -> 0 | E11: =E10*Premissas!$C$24 -> 0 | F11: =F10*Premissas!$C$24 -> 0 | G11: =G10*Premissas!$C$24 -> 0 | H11: =H10*Premissas!$C$24 -> 4 | I11: =I10*Premissas!$C$24 -> 2 | J11: =J10*Premissas!$C$24 -> 2 | K11: =K10*Premissas!$C$24 -> 4 | ... AA11: =AA10*Premissas!$C$24 -> 4 | AB11: =SUM(D11:O11) -> 26 | AC11: =SUM(P11:AA11) -> 48 | AD11: =SUM(D11:AA11) -> 74
B12: Clientes fechados (novos) | D12: =D11*Premissas!$C$25 -> 0 | E12: =E11*Premissas!$C$25 -> 0 | F12: =F11*Premissas!$C$25 -> 0 | G12: =G11*Premissas!$C$25 -> 0 | H12: =H11*Premissas!$C$25 -> 2 | I12: =I11*Premissas!$C$25 -> 1 | J12: =J11*Premissas!$C$25 -> 1 | K12: =K11*Premissas!$C$25 -> 2 | ... AA12: =AA11*Premissas!$C$25 -> 2 | AB12: =SUM(D12:O12) -> 13 | AC12: =SUM(P12:AA12) -> 24 | AD12: =SUM(D12:AA12) -> 37
B14: Funil padrão (regime de maturidade, Seção 19)
B15: Etapa | C15: Quantidade | D15: Conversão
B16: Leads | C16: 100
B17: Qualificados | C17: =C16*Premissas!$C$22 -> 20 | D17: =Premissas!$C$22 -> 0.2
B18: Demonstrações | C18: =C17*Premissas!$C$23 -> 8 | D18: =Premissas!$C$23 -> 0.4
B19: Propostas | C19: =C18*Premissas!$C$24 -> 4 | D19: =Premissas!$C$24 -> 0.5
B20: Clientes fechados | C20: =C19*Premissas!$C$25 -> 2 | D20: =Premissas!$C$25 -> 0.5

Sheet Receita e Clientes
B2: Clientes e receita mês a mês
B3: Receita em regime de competência: o mês em que o serviço é prestado e faturado.
B5: Linha | D5: M1 | E5: M2 | F5: M3 | G5: M4 | H5: M5 | I5: M6 | J5: M7 | K5: M8 | L5: M9 | M5: M10 | N5: M11 | O5: M12 | P5: M13 | Q5: M14 | R5: M15 | S5: M16 | T5: M17 | U5: M18 | V5: M19 | W5: M20 | X5: M21 | Y5: M22 | Z5: M23 | AA5: M24 | AB5: Ano 1 | AC5: Ano 2 | AD5: Total 24m
B6: Nº do mês | C6: 0 | D6: 1 | E6: 2 | F6: 3 | G6: 4 | H6: 5 | I6: 6 | J6: 7 | K6: 8 | L6: 9 | M6: 10 | N6: 11 | O6: 12 | P6: 13 | Q6: 14 | R6: 15 | S6: 16 | T6: 17 | U6: 18 | V6: 19 | W6: 20 | X6: 21 | Y6: 22 | Z6: 23 | AA6: 24
B7: Clientes-piloto (usam sem pagar) | D7: =IF(D6<Premissas!$C$29,Premissas!$C$28,0) -> 3 | E7: =IF(E6<Premissas!$C$29,Premissas!$C$28,0) -> 3 | F7: =IF(F6<Premissas!$C$29,Premissas!$C$28,0) -> 3 | G7: =IF(G6<Premissas!$C$29,Premissas!$C$28,0) -> 0 | H7: =IF(H6<Premissas!$C$29,Premissas!$C$28,0) -> 0 | I7: =IF(I6<Premissas!$C$29,Premissas!$C$28,0) -> 0 | J7: =IF(J6<Premissas!$C$29,Premissas!$C$28,0) -> 0 | K7: =IF(K6<Premissas!$C$29,Premissas!$C$28,0) -> 0 | ... AA7: =IF(AA6<Premissas!$C$29,Premissas!$C$28,0) -> 0 | AB7: =O7 -> 0 | AC7: =AA7 -> 0 | AD7: =AA7 -> 0
B8: Piloto convertido em pagante | D8: =IF(D6=Premissas!$C$29,Premissas!$C$28,0) -> 0 | E8: =IF(E6=Premissas!$C$29,Premissas!$C$28,0) -> 0 | F8: =IF(F6=Premissas!$C$29,Premissas!$C$28,0) -> 0 | G8: =IF(G6=Premissas!$C$29,Premissas!$C$28,0) -> 3 | H8: =IF(H6=Premissas!$C$29,Premissas!$C$28,0) -> 0 | I8: =IF(I6=Premissas!$C$29,Premissas!$C$28,0) -> 0 | J8: =IF(J6=Premissas!$C$29,Premissas!$C$28,0) -> 0 | K8: =IF(K6=Premissas!$C$29,Premissas!$C$28,0) -> 0 | ... AA8: =IF(AA6=Premissas!$C$29,Premissas!$C$28,0) -> 0 | AB8: =SUM(D8:O8) -> 3 | AC8: =SUM(P8:AA8) -> 0 | AD8: =SUM(D8:AA8) -> 3
B9: Novos clientes vindos do funil | D9: ='Funil de Vendas'!D12 -> 0 | E9: ='Funil de Vendas'!E12 -> 0 | F9: ='Funil de Vendas'!F12 -> 0 | G9: ='Funil de Vendas'!G12 -> 0 | H9: ='Funil de Vendas'!H12 -> 2 | I9: ='Funil de Vendas'!I12 -> 1 | J9: ='Funil de Vendas'!J12 -> 1 | K9: ='Funil de Vendas'!K12 -> 2 | ... AA9: ='Funil de Vendas'!AA12 -> 2 | AB9: =SUM(D9:O9) -> 13 | AC9: =SUM(P9:AA9) -> 24 | AD9: =SUM(D9:AA9) -> 37
B10: Cancelamentos | D10: =IF(D6>=Premissas!$C$33,C11*Premissas!$C$11,0) -> 0 | E10: =IF(E6>=Premissas!$C$33,D11*Premissas!$C$11,0) -> 0 | F10: =IF(F6>=Premissas!$C$33,E11*Premissas!$C$11,0) -> 0 | G10: =IF(G6>=Premissas!$C$33,F11*Premissas!$C$11,0) -> 0 | H10: =IF(H6>=Premissas!$C$33,G11*Premissas!$C$11,0) -> 0 | I10: =IF(I6>=Premissas!$C$33,H11*Premissas!$C$11,0) -> 0 | J10: =IF(J6>=Premissas!$C$33,I11*Premissas!$C$11,0) -> 0 | K10: =IF(K6>=Premissas!$C$33,J11*Premissas!$C$11,0) -> 0 | ... AA10: =IF(AA6>=Premissas!$C$33,Z11*Premissas!$C$11,0) -> 0 | AB10: =SUM(D10:O10) -> 0 | AC10: =SUM(P10:AA10) -> 0 | AD10: =SUM(D10:AA10) -> 0
B11: Clientes pagantes ativos (fim do mês) | D11: =N(C11)+D8+D9-D10 -> 0 | E11: =N(D11)+E8+E9-E10 -> 0 | F11: =N(E11)+F8+F9-F10 -> 0 | G11: =N(F11)+G8+G9-G10 -> 3 | H11: =N(G11)+H8+H9-H10 -> 5 | I11: =N(H11)+I8+I9-I10 -> 6 | J11: =N(I11)+J8+J9-J10 -> 7 | K11: =N(J11)+K8+K9-K10 -> 9 | ... AA11: =N(Z11)+AA8+AA9-AA10 -> 40 | AB11: =O11 -> 16 | AC11: =AA11 -> 40 | AD11: =AA11 -> 40
B12: Clientes atendidos (pagantes + piloto) | D12: =D11+D7 -> 3 | E12: =E11+E7 -> 3 | F12: =F11+F7 -> 3 | G12: =G11+G7 -> 3 | H12: =H11+H7 -> 5 | I12: =I11+I7 -> 6 | J12: =J11+J7 -> 7 | K12: =K11+K7 -> 9 | ... AA12: =AA11+AA7 -> 40 | AB12: =O12 -> 16 | AC12: =AA12 -> 40 | AD12: =AA12 -> 40
B13: Colaboradores atendidos na plataforma | D13: =D12*Premissas!$C$14 -> 900 | E13: =E12*Premissas!$C$14 -> 900 | F13: =F12*Premissas!$C$14 -> 900 | G13: =G12*Premissas!$C$14 -> 900 | H13: =H12*Premissas!$C$14 -> 1500 | I13: =I12*Premissas!$C$14 -> 1800 | J13: =J12*Premissas!$C$14 -> 2100 | K13: =K12*Premissas!$C$14 -> 2700 | ... AA13: =AA12*Premissas!$C$14 -> 12000 | AB13: =O13 -> 4800 | AC13: =AA13 -> 12000 | AD13: =AA13 -> 12000
B14: Ticket médio por cliente (ARPA) | D14: =Premissas!$C$17 -> 7500 | E14: =Premissas!$C$17 -> 7500 | F14: =Premissas!$C$17 -> 7500 | G14: =Premissas!$C$17 -> 7500 | H14: =Premissas!$C$17 -> 7500 | I14: =Premissas!$C$17 -> 7500 | J14: =Premissas!$C$17 -> 7500 | K14: =Premissas!$C$17 -> 7500 | ... AA14: =Premissas!$C$17 -> 7500 | AB14: =AVERAGE(D14:O14) -> 7500 | AC14: =AVERAGE(P14:AA14) -> 7500 | AD14: =AVERAGE(D14:AA14) -> 7500
B15: RECEITA DO MÊS (MRR) | D15: =D11*D14 -> 0 | E15: =E11*E14 -> 0 | F15: =F11*F14 -> 0 | G15: =G11*G14 -> 22500 | H15: =H11*H14 -> 37500 | I15: =I11*I14 -> 45000 | J15: =J11*J14 -> 52500 | K15: =K11*K14 -> 67500 | ... AA15: =AA11*AA14 -> 300000 | AB15: =SUM(D15:O15) -> 615000 | AC15: =SUM(P15:AA15) -> 2610000 | AD15: =SUM(D15:AA15) -> 3225000
B16: Receita anualizada (ARR = MRR × 12) | D16: =D15*12 -> 0 | E16: =E15*12 -> 0 | F16: =F15*12 -> 0 | G16: =G15*12 -> 270000 | H16: =H15*12 -> 450000 | I16: =I15*12 -> 540000 | J16: =J15*12 -> 630000 | K16: =K15*12 -> 810000 | ... AA16: =AA15*12 -> 3600000 | AB16: =O16 -> 1440000 | AC16: =AA16 -> 3600000 | AD16: =AA16 -> 3600000
B18: Conferência com a documentação (vale no cenário Base)
B19: Marco | C19: Mês | D19: Documentação | E19: Modelo | F19: Situação
B20: Clientes pagantes ativos | C20: 4 | D20: 3 | E20: =G11 -> 3 | F20: =IF(ABS(E20-D20)<0.01,"OK","difere") -> OK
B21: Clientes pagantes ativos | C21: 6 | D21: 6 | E21: =I11 -> 6 | F21: =IF(ABS(E21-D21)<0.01,"OK","difere") -> OK
B22: Clientes pagantes ativos | C22: 9 | D22: 10 | E22: =L11 -> 10 | F22: =IF(ABS(E22-D22)<0.01,"OK","difere") -> OK
B23: Clientes pagantes ativos | C23: 12 | D23: 16 | E23: =O11 -> 16 | F23: =IF(ABS(E23-D23)<0.01,"OK","difere") -> OK
B24: Clientes pagantes ativos | C24: 18 | D24: 28 | E24: =U11 -> 28 | F24: =IF(ABS(E24-D24)<0.01,"OK","difere") -> OK
B25: Clientes pagantes ativos | C25: 24 | D25: 40 | E25: =AA11 -> 40 | F25: =IF(ABS(E25-D25)<0.01,"OK","difere") -> OK
B26: ARR no M24 (SOM da Seção 5 = R$ 3,6 mi) | C26: 24 | D26: 3600000 | E26: =AA16 -> 3600000 | F26: =IF(ABS(E26-D26)<1,"OK","difere") -> OK

Sheet Custos Fixos
B2: Custos fixos
B3: Modelo do slide 7, detalhado por fase. Os totais por fase são os mesmos da Seção 20 (R$ 2,5 mil · 7 mil · 14 mil · 19 mil).
B5: Equipe contratada (CLT) | C5: Fase 1 · Piloto | D5: Fase 2 · Early adopters | E5: Fase 3a · Scale inicial | F5: Fase 3b · Scale maduro | G5: Salário
B6: Pessoas em tempo integral (FTE) por fase
B7: Customer Success (CS) | C7: 0 | D7: 0.5 | E7: 0.5 | F7: 1 | G7: 4000
B8: SDR (pré-vendas) | C8: 0 | D8: 0 | E8: 1 | F8: 1 | G8: 3500
B9: Sócios: sem pró-labore; remunerados por distribuição de lucros (ver aba Tributação).
B11: Descrição (modelo do slide 7) | C11: Fase 1 · Piloto | D11: Fase 2 · Early adopters | E11: Fase 3a · Scale inicial | F11: Fase 3b · Scale maduro | G11: Grupo | H11: Observação
B12: Aluguel (coworking) | C12: 0 | D12: 800 | E12: 1200 | F12: 1800 | G12: ocup
B13: IPTU | C13: 0 | D13: 0 | E13: 0 | F13: 0 | G13: ocup
B14: Água | C14: 0 | D14: 0 | E14: 0 | F14: 0 | G14: util
B15: Energia elétrica | C15: 0 | D15: 0 | E15: 0 | F15: 0 | G15: util
B16: Telefone, internet, celular | C16: 150 | D16: 250 | E16: 300 | F16: 400 | G16: util
B17: Manutenção dos equipamentos | C17: 0 | D17: 100 | E17: 150 | F17: 200 | G17: outros
B18: Material de limpeza | C18: 0 | D18: 0 | E18: 0 | F18: 0 | G18: limpeza
B19: Material de escritório | C19: 30 | D19: 50 | E19: 80 | F19: 120 | G19: outros
B20: Taxa de licença (TFE/alvará, mensalizada) | C20: 20 | D20: 20 | E20: 20 | F20: 20 | G20: outros
B21: ISS | C21: 0 | D21: 0 | E21: 0 | F21: 0 | G21: outros
B22: Propaganda e marketing (conteúdo, site, LinkedIn) | C22: 300 | D22: 900 | E22: 1400 | F22: 2000 | G22: outros
B23: Seguro empresarial / cyber | C23: 0 | D23: 0 | E23: 120 | F23: 160 | G23: seguro
... B27: Imprevistos | C27: 200 | D27: 180 | E27: 480 | F27: 250 | G27: outros
B28: Subtotal — demais custos fixos | C28: =SUM(C12:C27) -> 2500 | D28: =SUM(D12:D27) -> 4400 | E28: =SUM(E12:E27) -> 6850 | F28: =SUM(F12:F27) -> 9250
B29: Mão de obra (salários + encargos) | C29: =SUMPRODUCT(C7:C8,$G$7:$G$8)*(1+Premissas!$C$45) -> 0 | D29: =SUMPRODUCT(D7:D8,$G$7:$G$8)*(1+Premissas!$C$45) -> 2600 | E29: =SUMPRODUCT(E7:E8,$G$7:$G$8)*(1+Premissas!$C$45) -> 7150 | F29: =SUMPRODUCT(F7:F8,$G$7:$G$8)*(1+Premissas!$C$45) -> 9750
B30: TOTAL (custo fixo desembolsado por mês) | C30: =C28+C29 -> 2500 | D30: =D28+D29 -> 7000 | E30: =E28+E29 -> 14000 | F30: =F28+F29 -> 19000
B31: Total citado na Seção 20 da documentação | C31: 2500 | D31: 7000 | E31: 14000 | F31: 19000
B32: Confere? | C32: =IF(ABS(C30-C31)<0.5,"OK","difere") -> OK | D32: =IF(ABS(D30-D31)<0.5,"OK","difere") -> OK | E32: =IF(ABS(E30-E31)<0.5,"OK","difere") -> OK | F32: =IF(ABS(F30-F31)<0.5,"OK","difere") -> OK
B33: Depreciação e amortização (não sai do caixa) | C33: ='Investimento Inicial'!$C$39 -> 101.66667 | D33: ='Investimento Inicial'!$C$39 -> 101.66667 | E33: ='Investimento Inicial'!$C$39 -> 101.66667 | F33: ='Investimento Inicial'!$C$39 -> 101.66667
B35: Custos fixos mês a mês
B36: Linha | D36: M1 | E36: M2 | F36: M3 | G36: M4 | H36: M5 | I36: M6 | J36: M7 | K36: M8 | L36: M9 | M36: M10 | N36: M11 | O36: M12 | P36: M13 | Q36: M14 | R36: M15 | S36: M16 | T36: M17 | U36: M18 | V36: M19 | W36: M20 | X36: M21 | Y36: M22 | Z36: M23 | AA36: M24 | AB36: Ano 1 | AC36: Ano 2 | AD36: Total 24m
B37: Nº do mês | C37: 0 | D37: 1 | E37: 2 | F37: 3 | G37: 4 | H37: 5 | I37: 6 | J37: 7 | K37: 8 | L37: 9 | M37: 10 | N37: 11 | O37: 12 | P37: 13 | Q37: 14 | R37: 15 | S37: 16 | T37: 17 | U37: 18 | V37: 19 | W37: 20 | X37: 21 | Y37: 22 | Z37: 23 | AA37: 24
B38: Fase (1 a 4) | D38: =IF(D37<=Premissas!$C$30,1,IF(D37<=Premissas!$C$31,2,IF(D37<=Premissas!$C$32,3,4))) -> 1 | E38: =IF(E37<=Premissas!$C$30,1,IF(E37<=Premissas!$C$31,2,IF(E37<=Premissas!$C$32,3,4))) -> 1 | F38: =IF(F37<=Premissas!$C$30,1,IF(F37<=Premissas!$C$31,2,IF(F37<=Premissas!$C$32,3,4))) -> 1 | G38: =IF(G37<=Premissas!$C$30,1,IF(G37<=Premissas!$C$31,2,IF(G37<=Premissas!$C$32,3,4))) -> 2 | H38: =IF(H37<=Premissas!$C$30,1,IF(H37<=Premissas!$C$31,2,IF(H37<=Premissas!$C$32,3,4))) -> 2 | I38: =IF(I37<=Premissas!$C$30,1,IF(I37<=Premissas!$C$31,2,IF(I37<=Premissas!$C$32,3,4))) -> 2 | J38: =IF(J37<=Premissas!$C$30,1,IF(J37<=Premissas!$C$31,2,IF(J37<=Premissas!$C$32,3,4))) -> 2 | K38: =IF(K37<=Premissas!$C$30,1,IF(K37<=Premissas!$C$31,2,IF(K37<=Premissas!$C$32,3,4))) -> 2 | ... AA38: =IF(AA37<=Premissas!$C$30,1,IF(AA37<=Premissas!$C$31,2,IF(AA37<=Premissas!$C$32,3,4))) -> 4
B39: Mão de obra (salários + encargos) | D39: =INDEX($C$29:$F$29,D38) -> 0 | E39: =INDEX($C$29:$F$29,E38) -> 0 | F39: =INDEX($C$29:$F$29,F38) -> 0 | G39: =INDEX($C$29:$F$29,G38) -> 2600 | H39: =INDEX($C$29:$F$29,H38) -> 2600 | I39: =INDEX($C$29:$F$29,I38) -> 2600 | J39: =INDEX($C$29:$F$29,J38) -> 2600 | K39: =INDEX($C$29:$F$29,K38) -> 2600 | ... AA39: =INDEX($C$29:$F$29,AA38) -> 9750 | AB39: =SUM(D39:O39) -> 37050 | AC39: =SUM(P39:AA39) -> 101400 | AD39: =SUM(D39:AA39) -> 138450
B40: Demais custos fixos | D40: =INDEX($C$28:$F$28,D38) -> 2500 | E40: =INDEX($C$28:$F$28,E38) -> 2500 | F40: =INDEX($C$28:$F$28,F38) -> 2500 | G40: =INDEX($C$28:$F$28,G38) -> 4400 | H40: =INDEX($C$28:$F$28,H38) -> 4400 | I40: =INDEX($C$28:$F$28,I38) -> 4400 | J40: =INDEX($C$28:$F$28,J38) -> 4400 | K40: =INDEX($C$28:$F$28,K38) -> 4400 | ... AA40: =INDEX($C$28:$F$28,AA38) -> 9250 | AB40: =SUM(D40:O40) -> 54450 | AC40: =SUM(P40:AA40) -> 96600 | AD40: =SUM(D40:AA40) -> 151050
B41: Depreciação e amortização | D41: =INDEX($C$33:$F$33,D38) -> 101.66667 | E41: =INDEX($C$33:$F$33,E38) -> 101.66667 | F41: =INDEX($C$33:$F$33,F38) -> 101.66667 | G41: =INDEX($C$33:$F$33,G38) -> 101.66667 | H41: =INDEX($C$33:$F$33,H38) -> 101.66667 | I41: =INDEX($C$33:$F$33,I38) -> 101.66667 | J41: =INDEX($C$33:$F$33,J38) -> 101.66667 | K41: =INDEX($C$33:$F$33,K38) -> 101.66667 | ... AA41: =INDEX($C$33:$F$33,AA38) -> 101.66667 | AB41: =SUM(D41:O41) -> 1220 | AC41: =SUM(P41:AA41) -> 1220 | AD41: =SUM(D41:AA41) -> 2440
B42: TOTAL DE CUSTOS FIXOS DO MÊS | D42: =D39+D40+D41 -> 2601.6667 | E42: =E39+E40+E41 -> 2601.6667 | F42: =F39+F40+F41 -> 2601.6667 | G42: =G39+G40+G41 -> 7101.6667 | H42: =H39+H40+H41 -> 7101.6667 | I42: =I39+I40+I41 -> 7101.6667 | J42: =J39+J40+J41 -> 7101.6667 | K42: =K39+K40+K41 -> 7101.6667 | ... AA42: =AA39+AA40+AA41 -> 19101.667 | AB42: =SUM(D42:O42) -> 92720 | AC42: =SUM(P42:AA42) -> 199220 | AD42: =SUM(D42:AA42) -> 291940

Sheet Custos Variáveis
B2: Custos variáveis — estimativa
B3: Modelo do slide 8: ficha técnica por cliente e por colaborador, depois a projeção mês a mês.
B5: Ficha técnica — 1 cliente médio por mês | C5: R$ por cliente | D5: R$ por colaborador | E5: Equivale no slide a
B6: Processamento de IA (300 colaboradores) | C6: =Premissas!$C$37*Premissas!$C$14 -> 150 | D6: =C6/Premissas!$C$14 -> 0.5 | E6: Material
B7: DAS (alíquota efetiva média do Ano 2) | C7: =Premissas!$C$17*IFERROR(Tributação!AC20/Tributação!AC17,0) -> 1458.6519 | D7: =C7/Premissas!$C$14 -> 4.862173 | E7: Imposto
B8: Comissão de vendas | C8: =Premissas!$C$17*Premissas!$C$38 -> 375 | D8: =C8/Premissas!$C$14 -> 1.25 | E8: Mão de obra
B9: Tarifa de cobrança | C9: =Premissas!$C$39 -> 3 | D9: =C9/Premissas!$C$14 -> 0.01 | E9: Frete / entrega
B10: Perda com inadimplência | C10: =Premissas!$C$17*Premissas!$C$40 -> 75 | D10: =C10/Premissas!$C$14 -> 0.25 | E10: —
B11: Custo variável por cliente/mês | C11: =SUM(C6:C10) -> 2061.6519 | D11: =SUM(D6:D10) -> 6.872173
B12: Preço cobrado por cliente/mês (ARPA) | C12: =Premissas!$C$17 -> 7500 | D12: =Premissas!$C$16 -> 25
B13: Margem de contribuição por cliente/mês | C13: =C12-C11 -> 5438.3481 | D13: =D12-D11 -> 18.127827 | E13: =C13/C12 -> 0.72511308
B14: Entrega 100% digital: não há embalagem nem frete. O CAC (custo de conquistar o cliente) não entra aqui: é uma verba comercial planejada, tratada como despesa do período na DRE.
B16: Projeção mês a mês
B17: Linha | D17: M1 | E17: M2 | F17: M3 | G17: M4 | H17: M5 | I17: M6 | J17: M7 | K17: M8 | L17: M9 | M17: M10 | N17: M11 | O17: M12 | P17: M13 | Q17: M14 | R17: M15 | S17: M16 | T17: M17 | U17: M18 | V17: M19 | W17: M20 | X17: M21 | Y17: M22 | Z17: M23 | AA17: M24 | AB17: Ano 1 | AC17: Ano 2 | AD17: Total 24m
B18: Processamento de IA (insumo direto) | D18: ='Receita e Clientes'!D13*Premissas!$C$37 -> 450 | E18: ='Receita e Clientes'!E13*Premissas!$C$37 -> 450 | F18: ='Receita e Clientes'!F13*Premissas!$C$37 -> 450 | G18: ='Receita e Clientes'!G13*Premissas!$C$37 -> 450 | H18: ='Receita e Clientes'!H13*Premissas!$C$37 -> 750 | I18: ='Receita e Clientes'!I13*Premissas!$C$37 -> 900 | J18: ='Receita e Clientes'!J13*Premissas!$C$37 -> 1050 | K18: ='Receita e Clientes'!K13*Premissas!$C$37 -> 1350 | ... AA18: ='Receita e Clientes'!AA13*Premissas!$C$37 -> 6000 | AB18: =SUM(D18:O18) -> 13650 | AC18: =SUM(P18:AA18) -> 52200 | AD18: =SUM(D18:AA18) -> 65850
B19: Impostos sobre vendas (DAS) | D19: =Tributação!D20 -> 0 | E19: =Tributação!E20 -> 0 | F19: =Tributação!F20 -> 0 | G19: =Tributação!G20 -> 3487.5 | H19: =Tributação!H20 -> 5812.5 | I19: =Tributação!I20 -> 6975 | J19: =Tributação!J20 -> 8325 | K19: =Tributação!K20 -> 11025 | ... AA19: =Tributação!AA20 -> 61333.333 | AB19: =SUM(D19:O19) -> 102901.35 | AC19: =SUM(P19:AA19) -> 507610.86 | AD19: =SUM(D19:AA19) -> 610512.2
B20: Comissões de vendas | D20: ='Receita e Clientes'!D15*Premissas!$C$38 -> 0 | E20: ='Receita e Clientes'!E15*Premissas!$C$38 -> 0 | F20: ='Receita e Clientes'!F15*Premissas!$C$38 -> 0 | G20: ='Receita e Clientes'!G15*Premissas!$C$38 -> 1125 | H20: ='Receita e Clientes'!H15*Premissas!$C$38 -> 1875 | I20: ='Receita e Clientes'!I15*Premissas!$C$38 -> 2250 | J20: ='Receita e Clientes'!J15*Premissas!$C$38 -> 2625 | K20: ='Receita e Clientes'!K15*Premissas!$C$38 -> 3375 | ... AA20: ='Receita e Clientes'!AA15*Premissas!$C$38 -> 15000 | AB20: =SUM(D20:O20) -> 30750 | AC20: =SUM(P20:AA20) -> 130500 | AD20: =SUM(D20:AA20) -> 161250
B21: Tarifas de cobrança | D21: ='Receita e Clientes'!D11*Premissas!$C$39 -> 0 | E21: ='Receita e Clientes'!E11*Premissas!$C$39 -> 0 | F21: ='Receita e Clientes'!F11*Premissas!$C$39 -> 0 | G21: ='Receita e Clientes'!G11*Premissas!$C$39 -> 9 | H21: ='Receita e Clientes'!H11*Premissas!$C$39 -> 15 | I21: ='Receita e Clientes'!I11*Premissas!$C$39 -> 18 | J21: ='Receita e Clientes'!J11*Premissas!$C$39 -> 21 | K21: ='Receita e Clientes'!K11*Premissas!$C$39 -> 27 | ... AA21: ='Receita e Clientes'!AA11*Premissas!$C$39 -> 120 | AB21: =SUM(D21:O21) -> 246 | AC21: =SUM(P21:AA21) -> 1044 | AD21: =SUM(D21:AA21) -> 1290
B22: Perdas com inadimplência | D22: ='Receita e Clientes'!D15*Premissas!$C$40 -> 0 | E22: ='Receita e Clientes'!E15*Premissas!$C$40 -> 0 | F22: ='Receita e Clientes'!F15*Premissas!$C$40 -> 0 | G22: ='Receita e Clientes'!G15*Premissas!$C$40 -> 225 | H22: ='Receita e Clientes'!H15*Premissas!$C$40 -> 375 | I22: ='Receita e Clientes'!I15*Premissas!$C$40 -> 450 | J22: ='Receita e Clientes'!J15*Premissas!$C$40 -> 525 | K22: ='Receita e Clientes'!K15*Premissas!$C$40 -> 675 | ... AA22: ='Receita e Clientes'!AA15*Premissas!$C$40 -> 3000 | AB22: =SUM(D22:O22) -> 6150 | AC22: =SUM(P22:AA22) -> 26100 | AD22: =SUM(D22:AA22) -> 32250
B23: TOTAL DE CUSTOS VARIÁVEIS | D23: =SUM(D18:D22) -> 450 | E23: =SUM(E18:E22) -> 450 | F23: =SUM(F18:F22) -> 450 | G23: =SUM(G18:G22) -> 5296.5 | H23: =SUM(H18:H22) -> 8827.5 | I23: =SUM(I18:I22) -> 10593 | J23: =SUM(J18:J22) -> 12546 | K23: =SUM(K18:K22) -> 16452 | ... AA23: =SUM(AA18:AA22) -> 85453.333 | AB23: =SUM(D23:O23) -> 153697.35 | AC23: =SUM(P23:AA23) -> 717454.86 | AD23: =SUM(D23:AA23) -> 871152.2
B25: Aquisição de clientes (CAC × novos clientes do funil) | D25: ='Receita e Clientes'!D9*Premissas!$C$36 -> 0 | E25: ='Receita e Clientes'!E9*Premissas!$C$36 -> 0 | F25: ='Receita e Clientes'!F9*Premissas!$C$36 -> 0 | G25: ='Receita e Clientes'!G9*Premissas!$C$36 -> 0 | H25: ='Receita e Clientes'!H9*Premissas!$C$36 -> 6000 | I25: ='Receita e Clientes'!I9*Premissas!$C$36 -> 3000 | J25: ='Receita e Clientes'!J9*Premissas!$C$36 -> 3000 | K25: ='Receita e Clientes'!K9*Premissas!$C$36 -> 6000 | ... AA25: ='Receita e Clientes'!AA9*Premissas!$C$36 -> 6000 | AB25: =SUM(D25:O25) -> 39000 | AC25: =SUM(P25:AA25) -> 72000 | AD25: =SUM(D25:AA25) -> 111000

Sheet Custo Unitário e Preço
B2: Custo unitário e preço de venda
B3: Slide 9. A unidade vendida é 1 colaborador atendido por mês. Preço = custo unitário ÷ [100% − (% impostos + % lucro)].
B5: Item (por colaborador/mês) | C5: Momento 1 | D5: Momento 2 | E5: Momento 3 | F5: Fórmula
B6: Mês de referência (troque para ver outro volume) | C6: 4 | D6: 12 | E6: 24
B7: Volume: colaboradores atendidos no mês | C7: =INDEX('Receita e Clientes'!$D$13:$AA$13,C$6) -> 900 | D7: =INDEX('Receita e Clientes'!$D$13:$AA$13,D$6) -> 4800 | E7: =INDEX('Receita e Clientes'!$D$13:$AA$13,E$6) -> 12000 | F7: Clientes atendidos × 300.
B8: Custo unitário da mão de obra | C8: =IF(C7>0,INDEX('Custos Fixos'!$D$39:$AA$39,C$6)/C7,0) -> 2.8888889 | D8: =IF(D7>0,INDEX('Custos Fixos'!$D$39:$AA$39,D$6)/D7,0) -> 1.4895833 | E8: =IF(E7>0,INDEX('Custos Fixos'!$D$39:$AA$39,E$6)/E7,0) -> 0.8125 | F8: Custo da mão de obra ÷ volume produzido.
B9: Insumo direto (IA + cobrança) por colaborador | C9: =Premissas!$C$37+Premissas!$C$39/Premissas!$C$14 -> 0.51 | D9: =Premissas!$C$37+Premissas!$C$39/Premissas!$C$14 -> 0.51 | E9: =Premissas!$C$37+Premissas!$C$39/Premissas!$C$14 -> 0.51 | F9: No slide, "MP": processamento de IA + tarifa da fatura.
B10: Custo fixo unitário | C10: =IF(C7>0,(INDEX('Custos Fixos'!$D$40:$AA$40,C$6)+INDEX('Custos Fixos'!$D$41:$AA$41,C$6))/C7,0) -> 5.0018519 | D10: =IF(D7>0,(INDEX('Custos Fixos'!$D$40:$AA$40,D$6)+INDEX('Custos Fixos'!$D$41:$AA$41,D$6))/D7,0) -> 1.4482639 | E10: =IF(E7>0,(INDEX('Custos Fixos'!$D$40:$AA$40,E$6)+INDEX('Custos Fixos'!$D$41:$AA$41,E$6))/E7,0) -> 0.77930556 | F10: Custo fixo total (sem mão de obra) ÷ volume produzido.
B11: CUSTO UNITÁRIO (MDO + MP + custo fixo unitário) | C11: =C8+C9+C10 -> 8.4007407 | D11: =D8+D9+D10 -> 3.4478472 | E11: =E8+E9+E10 -> 2.1018056 | F11: Fórmula do slide 9.
B12: % impostos e gastos sobre o preço (DAS + comissão + inadimplência) | C12: =INDEX(Tributação!$D$19:$AA$19,C$6)+Premissas!$C$38+Premissas!$C$40 -> 0.215 | D12: =INDEX(Tributação!$D$19:$AA$19,D$6)+Premissas!$C$38+Premissas!$C$40 -> 0.23666667 | E12: =INDEX(Tributação!$D$19:$AA$19,E$6)+Premissas!$C$38+Premissas!$C$40 -> 0.26444444 | F12: Alíquota efetiva do DAS no mês + comissão + inadimplência.
B13: % lucro desejado | C13: =Premissas!$C$59 -> 0.2 | D13: =Premissas!$C$59 -> 0.2 | E13: =Premissas!$C$59 -> 0.2 | F13: Premissas.
B14: PREÇO DE VENDA CALCULADO = custo ÷ [100% − (% impostos + % lucro)] | C14: =IF(1-(C12+C13)>0,C11/(1-(C12+C13)),0) -> 14.360241 | D14: =IF(1-(D12+D13)>0,D11/(1-(D12+D13)),0) -> 6.1204389 | E14: =IF(1-(E12+E13)>0,E11/(1-(E12+E13)),0) -> 3.9245332 | F14: Preço que cobre custos, impostos e o lucro desejado nesse volume.
B15: Preço médio praticado | C15: =Premissas!$C$16 -> 25 | D15: =Premissas!$C$16 -> 25 | E15: =Premissas!$C$16 -> 25 | F15: Premissas.
B16: Folga do preço praticado sobre o calculado | C16: =IF(C14>0,C15/C14-1,0) -> 0.74091791 | D16: =IF(D14>0,D15/D14-1,0) -> 3.0846744 | E16: =IF(E14>0,E15/E14-1,0) -> 5.3701844 | F16: Quanto o preço de mercado está acima do preço mínimo com lucro.
B18: Margem de cada plano no Momento 2
B19: Plano | C19: Preço/colab | D19: Custo + impostos | E19: Lucro por colab
B20: Starter (100–300 colaboradores) | C20: =Premissas!$C$18 -> 29 | D20: =$D$11+C20*$D$12 -> 10.311181 | E20: =C20-D20 -> 18.688819 | F20: =IF(C20>0,E20/C20,0) -> 0.64444205
B21: Growth (301–800) | C21: =Premissas!$C$19 -> 24 | D21: =$D$11+C21*$D$12 -> 9.1278472 | E21: =C21-D21 -> 14.872153 | F21: =IF(C21>0,E21/C21,0) -> 0.61967303
B22: Enterprise (801–2.000) | C22: =Premissas!$C$20 -> 19 | D22: =$D$11+C22*$D$12 -> 7.9445139 | E22: =C22-D22 -> 11.055486 | F22: =IF(C22>0,E22/C22,0) -> 0.58186769
B23: O custo unitário cai muito com o volume: o custo fixo é diluído em mais colaboradores. É a economia de escala típica de software.

Sheet Tributação
B2: Impostos — Simples Nacional
B3: DAS sobre a receita, com a receita bruta dos últimos 12 meses (RBT12). Inclui IRPJ, CSLL, PIS, Cofins, CPP e ISS.
B5: Tabelas 2026 (LC 123/2006)
B6: Faixa | C6: RBT12 de (R$) | D6: até (R$) | E6: Anexo III nominal | F6: III: deduzir (R$) | G6: Anexo V nominal | H6: V: deduzir (R$)
B7: 1ª | C7: 0 | D7: 180000 | E7: 0.06 | F7: 0 | G7: 0.155 | H7: 0
B8: 2ª | C8: 180000.01 | D8: 360000 | E8: 0.112 | F8: 9360 | G8: 0.18 | H8: 4500
B9: 3ª | C9: 360000.01 | D9: 720000 | E9: 0.135 | F9: 17640 | G9: 0.195 | H9: 9900
B10: 4ª | C10: 720000.01 | D10: 1800000 | E10: 0.16 | F10: 35640 | G10: 0.205 | H10: 17100
B11: 5ª | C11: 1800000 | D11: 3600000 | E11: 0.21 | F11: 125640 | G11: 0.23 | H11: 62100
B12: 6ª | C12: 3600000 | D12: 4800000 | E12: 0.33 | F12: 648000 | G12: 0.305 | H12: 540000
B13: Fonte: LC 123/2006, Anexos III e V (tabelas vigentes em 2026). SaaS (CNAE 6311-9/00 ou 6203-1/00) fica no Anexo V, ou no Anexo III quando o Fator R ≥ 28%.
B15: Cálculo mês a mês | D15: M1 | E15: M2 | F15: M3 | G15: M4 | H15: M5 | I15: M6 | J15: M7 | K15: M8 | L15: M9 | M15: M10 | N15: M11 | O15: M12 | P15: M13 | Q15: M14 | R15: M15 | S15: M16 | T15: M17 | U15: M18 | V15: M19 | W15: M20 | X15: M21 | Y15: M22 | Z15: M23 | AA15: M24 | AB15: Ano 1 | AC15: Ano 2 | AD15: Total 24m
B16: Nº do mês | C16: 0 | D16: 1 | E16: 2 | F16: 3 | G16: 4 | H16: 5 | I16: 6 | J16: 7 | K16: 8 | L16: 9 | M16: 10 | N16: 11 | O16: 12 | P16: 13 | Q16: 14 | R16: 15 | S16: 16 | T16: 17 | U16: 18 | V16: 19 | W16: 20 | X16: 21 | Y16: 22 | Z16: 23 | AA16: 24
B17: Receita do mês | D17: ='Receita e Clientes'!D15 -> 0 | E17: ='Receita e Clientes'!E15 -> 0 | F17: ='Receita e Clientes'!F15 -> 0 | G17: ='Receita e Clientes'!G15 -> 22500 | H17: ='Receita e Clientes'!H15 -> 37500 | I17: ='Receita e Clientes'!I15 -> 45000 | J17: ='Receita e Clientes'!J15 -> 52500 | K17: ='Receita e Clientes'!K15 -> 67500 | ... AA17: ='Receita e Clientes'!AA15 -> 300000 | AB17: =SUM(D17:O17) -> 615000 | AC17: =SUM(P17:AA17) -> 2610000 | AD17: =SUM(D17:AA17) -> 3225000
B18: RBT12 — receita bruta dos 12 meses anteriores | D18: =D17*12 -> 0 | E18: =SUM(D17:D17)/1*12 -> 0 | F18: =SUM(D17:E17)/2*12 -> 0 | G18: =SUM(D17:F17)/3*12 -> 0 | H18: =SUM(D17:G17)/4*12 -> 67500 | I18: =SUM(D17:H17)/5*12 -> 144000 | J18: =SUM(D17:I17)/6*12 -> 210000 | K18: =SUM(D17:J17)/7*12 -> 270000 | L18: =SUM(D17:K17)/8*12 -> 337500 | M18: =SUM(D17:L17)/9*12 -> 400000 | N18: =SUM(D17:M17)/10*12 -> 468000 | O18: =SUM(D17:N17)/11*12 -> 540000 | P18: =SUM(D17:O17) -> 615000 | Q18: =SUM(E17:P17) -> 750000 | R18: =SUM(F17:Q17) -> 900000 | S18: =SUM(G17:R17) -> 1065000 | T18: =SUM(H17:S17) -> 1222500 | U18: =SUM(I17:T17) -> 1380000 | V18: =SUM(J17:U17) -> 1545000 | W18: =SUM(K17:V17) -> 1717500 | ... AA18: =SUM(O17:Z17) -> 2430000
B19: Alíquota efetiva — Anexo V | D19: =IF(D18<=180000,$G$7,(D18*INDEX($G$7:$G$12,MATCH(D18,$C$7:$C$12,1))-INDEX($H$7:$H$12,MATCH(D18,$C$7:$C$12,1)))/D18) -> 0.155 | E19: =IF(E18<=180000,$G$7,(E18*INDEX($G$7:$G$12,MATCH(E18,$C$7:$C$12,1))-INDEX($H$7:$H$12,MATCH(E18,$C$7:$C$12,1)))/E18) -> 0.155 | F19: =IF(F18<=180000,$G$7,(F18*INDEX($G$7:$G$12,MATCH(F18,$C$7:$C$12,1))-INDEX($H$7:$H$12,MATCH(F18,$C$7:$C$12,1)))/F18) -> 0.155 | G19: =IF(G18<=180000,$G$7,(G18*INDEX($G$7:$G$12,MATCH(G18,$C$7:$C$12,1))-INDEX($H$7:$H$12,MATCH(G18,$C$7:$C$12,1)))/G18) -> 0.155 | H19: =IF(H18<=180000,$G$7,(H18*INDEX($G$7:$G$12,MATCH(H18,$C$7:$C$12,1))-INDEX($H$7:$H$12,MATCH(H18,$C$7:$C$12,1)))/H18) -> 0.155 | I19: =IF(I18<=180000,$G$7,(I18*INDEX($G$7:$G$12,MATCH(I18,$C$7:$C$12,1))-INDEX($H$7:$H$12,MATCH(I18,$C$7:$C$12,1)))/I18) -> 0.155 | J19: =IF(J18<=180000,$G$7,(J18*INDEX($G$7:$G$12,MATCH(J18,$C$7:$C$12,1))-INDEX($H$7:$H$12,MATCH(J18,$C$7:$C$12,1)))/J18) -> 0.15857143 | K19: =IF(K18<=180000,$G$7,(K18*INDEX($G$7:$G$12,MATCH(K18,$C$7:$C$12,1))-INDEX($H$7:$H$12,MATCH(K18,$C$7:$C$12,1)))/K18) -> 0.16333333 | ... AA19: =IF(AA18<=180000,$G$7,(AA18*INDEX($G$7:$G$12,MATCH(AA18,$C$7:$C$12,1))-INDEX($H$7:$H$12,MATCH(AA18,$C$7:$C$12,1)))/AA18) -> 0.20444444
B20: DAS A PAGAR (Anexo V — regime adotado) | D20: =D17*D19 -> 0 | E20: =E17*E19 -> 0 | F20: =F17*F19 -> 0 | G20: =G17*G19 -> 3487.5 | H20: =H17*H19 -> 5812.5 | I20: =I17*I19 -> 6975 | J20: =J17*J19 -> 8325 | K20: =K17*K19 -> 11025 | ... AA20: =AA17*AA19 -> 61333.333 | AB20: =SUM(D20:O20) -> 102901.35 | AC20: =SUM(P20:AA20) -> 507610.86 | AD20: =SUM(D20:AA20) -> 610512.2
B22: Simulação: e se os sócios tirassem pró-labore para chegar ao Fator R de 28% (Anexo III)?
B23: Alíquota efetiva — Anexo III | D23: =IF(D18<=180000,$E$7,(D18*INDEX($E$7:$E$12,MATCH(D18,$C$7:$C$12,1))-INDEX($F$7:$F$12,MATCH(D18,$C$7:$C$12,1)))/D18) -> 0.06 | E23: =IF(E18<=180000,$E$7,(E18*INDEX($E$7:$E$12,MATCH(E18,$C$7:$C$12,1))-INDEX($F$7:$F$12,MATCH(E18,$C$7:$C$12,1)))/E18) -> 0.06 | F23: =IF(F18<=180000,$E$7,(F18*INDEX($E$7:$E$12,MATCH(F18,$C$7:$C$12,1))-INDEX($F$7:$F$12,MATCH(F18,$C$7:$C$12,1)))/F18) -> 0.06 | G23: =IF(G18<=180000,$E$7,(G18*INDEX($E$7:$E$12,MATCH(G18,$C$7:$C$12,1))-INDEX($F$7:$F$12,MATCH(G18,$C$7:$C$12,1)))/G18) -> 0.06 | H23: =IF(H18<=180000,$E$7,(H18*INDEX($E$7:$E$12,MATCH(H18,$C$7:$C$12,1))-INDEX($F$7:$F$12,MATCH(H18,$C$7:$C$12,1)))/H18) -> 0.06 | I23: =IF(I18<=180000,$E$7,(I18*INDEX($E$7:$E$12,MATCH(I18,$C$7:$C$12,1))-INDEX($F$7:$F$12,MATCH(I18,$C$7:$C$12,1)))/I18) -> 0.06 | J23: =IF(J18<=180000,$E$7,(J18*INDEX($E$7:$E$12,MATCH(J18,$C$7:$C$12,1))-INDEX($F$7:$F$12,MATCH(J18,$C$7:$C$12,1)))/J18) -> 0.067428571 | K23: =IF(K18<=180000,$E$7,(K18*INDEX($E$7:$E$12,MATCH(K18,$C$7:$C$12,1))-INDEX($F$7:$F$12,MATCH(K18,$C$7:$C$12,1)))/K18) -> 0.077333333 | ... AA23: =IF(AA18<=180000,$E$7,(AA18*INDEX($E$7:$E$12,MATCH(AA18,$C$7:$C$12,1))-INDEX($F$7:$F$12,MATCH(AA18,$C$7:$C$12,1)))/AA18) -> 0.1582963
B24: DAS no Anexo III | D24: =D17*D23 -> 0 | E24: =E17*E23 -> 0 | F24: =F17*F23 -> 0 | G24: =G17*G23 -> 1350 | H24: =H17*H23 -> 2250 | I24: =I17*I23 -> 2700 | J24: =J17*J23 -> 3540 | K24: =K17*K23 -> 5220 | ... AA24: =AA17*AA23 -> 47488.889 | AB24: =SUM(D24:O24) -> 52058.308 | AC24: =SUM(P24:AA24) -> 360123.44 | AD24: =SUM(D24:AA24) -> 412181.75
B25: Folha CLT do mês (salários + encargos) | D25: ='Custos Fixos'!D39 -> 0 | E25: ='Custos Fixos'!E39 -> 0 | F25: ='Custos Fixos'!F39 -> 0 | G25: ='Custos Fixos'!G39 -> 2600 | H25: ='Custos Fixos'!H39 -> 2600 | I25: ='Custos Fixos'!I39 -> 2600 | J25: ='Custos Fixos'!J39 -> 2600 | K25: ='Custos Fixos'!K39 -> 2600 | ... AA25: ='Custos Fixos'!AA39 -> 9750 | AB25: =SUM(D25:O25) -> 37050 | AC25: =SUM(P25:AA25) -> 101400 | AD25: =SUM(D25:AA25) -> 138450
B26: Pró-labore total necessário para o Fator R | D26: =MAX(0,Premissas!$C$47*D18/12-D25) -> 0 | E26: =MAX(0,Premissas!$C$47*E18/12-E25) -> 0 | F26: =MAX(0,Premissas!$C$47*F18/12-F25) -> 0 | G26: =MAX(0,Premissas!$C$47*G18/12-G25) -> 0 | H26: =MAX(0,Premissas!$C$47*H18/12-H25) -> 0 | I26: =MAX(0,Premissas!$C$47*I18/12-I25) -> 760 | J26: =MAX(0,Premissas!$C$47*J18/12-J25) -> 2300 | K26: =MAX(0,Premissas!$C$47*K18/12-K25) -> 3700 | ... AA26: =MAX(0,Premissas!$C$47*AA18/12-AA25) -> 46950 | AB26: =SUM(D26:O26) -> 23438.333 | AC26: =SUM(P26:AA26) -> 314750 | AD26: =SUM(D26:AA26) -> 338188.33
B27: Pró-labore por sócio | D27: =D26/Premissas!$C$48 -> 0 | E27: =E26/Premissas!$C$48 -> 0 | F27: =F26/Premissas!$C$48 -> 0 | G27: =G26/Premissas!$C$48 -> 0 | H27: =H26/Premissas!$C$48 -> 0 | I27: =I26/Premissas!$C$48 -> 190 | J27: =J26/Premissas!$C$48 -> 575 | K27: =K26/Premissas!$C$48 -> 925 | ... AA27: =AA26/Premissas!$C$48 -> 11737.5 | AB27: =AVERAGE(D27:O27) -> 488.29861 | AC27: =AVERAGE(P27:AA27) -> 6557.2917 | AD27: =AVERAGE(D27:AA27) -> 3522.7951
B28: INSS dos sócios (11% até o teto) | D28: =Premissas!$C$50*MIN(D27,Premissas!$C$49)*Premissas!$C$48 -> 0 | E28: =Premissas!$C$50*MIN(E27,Premissas!$C$49)*Premissas!$C$48 -> 0 | F28: =Premissas!$C$50*MIN(F27,Premissas!$C$49)*Premissas!$C$48 -> 0 | G28: =Premissas!$C$50*MIN(G27,Premissas!$C$49)*Premissas!$C$48 -> 0 | H28: =Premissas!$C$50*MIN(H27,Premissas!$C$49)*Premissas!$C$48 -> 0 | I28: =Premissas!$C$50*MIN(I27,Premissas!$C$49)*Premissas!$C$48 -> 83.6 | J28: =Premissas!$C$50*MIN(J27,Premissas!$C$49)*Premissas!$C$48 -> 253 | K28: =Premissas!$C$50*MIN(K27,Premissas!$C$49)*Premissas!$C$48 -> 407 | ... AA28: =Premissas!$C$50*MIN(AA27,Premissas!$C$49)*Premissas!$C$48 -> 3729.242 | AB28: =SUM(D28:O28) -> 2578.2167 | AC28: =SUM(P28:AA28) -> 31653.468 | AD28: =SUM(D28:AA28) -> 34231.685
B29: IRPF dos sócios sobre o pró-labore | D29: =MAX(0,IF(MAX(0,D27-Premissas!$C$50*MIN(D27,Premissas!$C$49))<=2428.8,0,IF(MAX(0,D27-Premissas!$C$50*MIN(D27,Premissas!$C$49))<=2826.65,MAX(0,D27-Premissas!$C$50*MIN(D27,Premissas!$C$49))*0.075-182.16,IF(MAX(0,D27-Premissas!$C$50*MIN(D27,Premissas!$C$49))<=3751.05,MAX(0,D27-Premissas!$C$50*MIN(D27,Premissas!$C$49))*0.15-394.16,IF(MAX(0,D27-Premissas!$C$50*MIN(D27,Premissas!$C$49))<=4664.68,MAX(0,D27-Premissas!$C$50*MIN(D27,Premissas!$C$49))*0.225-675.49,MAX(0,D27-Premissas!$C$50*MIN(D27,Premissas!$C$49))*0.275-908.73))))-IF(D27<=5000,312.89,IF(D27<=7350,MAX(0,978.62-0.133145*D27),0)))*Premissas!$C$48 -> 0 | E29: =MAX(0,IF(MAX(0,E27-Premissas!$C$50*MIN(E27,Premissas!$C$49))<=2428.8,0,IF(MAX(0,E27-Premissas!$C$50*MIN(E27,Premissas!$C$49))<=2826.65,MAX(0,E27-Premissas!$C$50*MIN(E27,Premissas!$C$49))*0.075-182.16,IF(MAX(0,E27-Premissas!$C$50*MIN(E27,Premissas!$C$49))<=3751.05,MAX(0,E27-Premissas!$C$50*MIN(E27,Premissas!$C$49))*0.15-394.16,IF(MAX(0,E27-Premissas!$C$50*MIN(E27,Premissas!$C$49))<=4664.68,MAX(0,E27-Premissas!$C$50*MIN(E27,Premissas!$C$49))*0.225-675.49,MAX(0,E27-Premissas!$C$50*MIN(E27,Premissas!$C$49))*0.275-908.73))))-IF(E27<=5000,312.89,IF(E27<=7350,MAX(0,978.62-0.133145*E27),0)))*Premissas!$C$48 -> 0 | F29: =MAX(0,IF(MAX(0,F27-Premissas!$C$50*MIN(F27,Premissas!$C$49))<=2428.8,0,IF(MAX(0,F27-Premissas!$C$50*MIN(F27,Premissas!$C$49))<=2826.65,MAX(0,F27-Premissas!$C$50*MIN(F27,Premissas!$C$49))*0.075-182.16,IF(MAX(0,F27-Premissas!$C$50*MIN(F27,Premissas!$C$49))<=3751.05,MAX(0,F27-Premissas!$C$50*MIN(F27,Premissas!$C$49))*0.15-394.16,IF(MAX(0,F27-Premissas!$C$50*MIN(F27,Premissas!$C$49))<=4664.68,MAX(0,F27-Premissas!$C$50*MIN(F27,Premissas!$C$49))*0.225-675.49,MAX(0,F27-Premissas!$C$50*MIN(F27,Premissas!$C$49))*0.275-908.73))))-IF(F27<=5000,312.89,IF(F27<=7350,MAX(0,978.62-0.133145*F27),0)))*Premissas!$C$48 -> 0 | G29: =MAX(0,IF(MAX(0,G27-Premissas!$C$50*MIN(G27,Premissas!$C$49))<=2428.8,0,IF(MAX(0,G27-Premissas!$C$50*MIN(G27,Premissas!$C$49))<=2826.65,MAX(0,G27-Premissas!$C$50*MIN(G27,Premissas!$C$49))*0.075-182.16,IF(MAX(0,G27-Premissas!$C$50*MIN(G27,Premissas!$C$49))<=3751.05,MAX(0,G27-Premissas!$C$50*MIN(G27,Premissas!$C$49))*0.15-394.16,IF(MAX(0,G27-Premissas!$C$50*MIN(G27,Premissas!$C$49))<=4664.68,MAX(0,G27-Premissas!$C$50*MIN(G27,Premissas!$C$49))*0.225-675.49,MAX(0,G27-Premissas!$C$50*MIN(G27,Premissas!$C$49))*0.275-908.73))))-IF(G27<=5000,312.89,IF(G27<=7350,MAX(0,978.62-0.133145*G27),0)))*Premissas!$C$48 -> 0 | H29: =MAX(0,IF(MAX(0,H27-Premissas!$C$50*MIN(H27,Premissas!$C$49))<=2428.8,0,IF(MAX(0,H27-Premissas!$C$50*MIN(H27,Premissas!$C$49))<=2826.65,MAX(0,H27-Premissas!$C$50*MIN(H27,Premissas!$C$49))*0.075-182.16,IF(MAX(0,H27-Premissas!$C$50*MIN(H27,Premissas!$C$49))<=3751.05,MAX(0,H27-Premissas!$C$50*MIN(H27,Premissas!$C$49))*0.15-394.16,IF(MAX(0,H27-Premissas!$C$50*MIN(H27,Premissas!$C$49))<=4664.68,MAX(0,H27-Premissas!$C$50*MIN(H27,Premissas!$C$49))*0.225-675.49,MAX(0,H27-Premissas!$C$50*MIN(H27,Premissas!$C$49))*0.275-908.73))))-IF(H27<=5000,312.89,IF(H27<=7350,MAX(0,978.62-0.133145*H27),0)))*Premissas!$C$48 -> 0 | I29: =MAX(0,IF(MAX(0,I27-Premissas!$C$50*MIN(I27,Premissas!$C$49))<=2428.8,0,IF(MAX(0,I27-Premissas!$C$50*MIN(I27,Premissas!$C$49))<=2826.65,MAX(0,I27-Premissas!$C$50*MIN(I27,Premissas!$C$49))*0.075-182.16,IF(MAX(0,I27-Premissas!$C$50*MIN(I27,Premissas!$C$49))<=3751.05,MAX(0,I27-Premissas!$C$50*MIN(I27,Premissas!$C$49))*0.15-394.16,IF(MAX(0,I27-Premissas!$C$50*MIN(I27,Premissas!$C$49))<=4664.68,MAX(0,I27-Premissas!$C$50*MIN(I27,Premissas!$C$49))*0.225-675.49,MAX(0,I27-Premissas!$C$50*MIN(I27,Premissas!$C$49))*0.275-908.73))))-IF(I27<=5000,312.89,IF(I27<=7350,MAX(0,978.62-0.133145*I27),0)))*Premissas!$C$48 -> 0 | J29: =MAX(0,IF(MAX(0,J27-Premissas!$C$50*MIN(J27,Premissas!$C$49))<=2428.8,0,IF(MAX(0,J27-Premissas!$C$50*MIN(J27,Premissas!$C$49))<=2826.65,MAX(0,J27-Premissas!$C$50*MIN(J27,Premissas!$C$49))*0.075-182.16,IF(MAX(0,J27-Premissas!$C$50*MIN(J27,Premissas!$C$49))<=3751.05,MAX(0,J27-Premissas!$C$50*MIN(J27,Premissas!$C$49))*0.15-394.16,IF(MAX(0,J27-Premissas!$C$50*MIN(J27,Premissas!$C$49))<=4664.68,MAX(0,J27-Premissas!$C$50*MIN(J27,Premissas!$C$49))*0.225-675.49,MAX(0,J27-Premissas!$C$50*MIN(J27,Premissas!$C$49))*0.275-908.73))))-IF(J27<=5000,312.89,IF(J27<=7350,MAX(0,978.62-0.133145*J27),0)))*Premissas!$C$48 -> 0 | K29: =MAX(0,IF(MAX(0,K27-Premissas!$C$50*MIN(K27,Premissas!$C$49))<=2428.8,0,IF(MAX(0,K27-Premissas!$C$50*MIN(K27,Premissas!$C$49))<=2826.65,MAX(0,K27-Premissas!$C$50*MIN(K27,Premissas!$C$49))*0.075-182.16,IF(MAX(0,K27-Premissas!$C$50*MIN(K27,Premissas!$C$49))<=3751.05,MAX(0,K27-Premissas!$C$50*MIN(K27,Premissas!$C$49))*0.15-394.16,IF(MAX(0,K27-Premissas!$C$50*MIN(K27,Premissas!$C$49))<=4664.68,MAX(0,K27-Premissas!$C$50*MIN(K27,Premissas!$C$49))*0.225-675.49,MAX(0,K27-Premissas!$C$50*MIN(K27,Premissas!$C$49))*0.275-908.73))))-IF(K27<=5000,312.89,IF(K27<=7350,MAX(0,978.62-0.133145*K27),0)))*Premissas!$C$48 -> 0 | ... AA29: =MAX(0,IF(MAX(0,AA27-Premissas!$C$50*MIN(AA27,Premissas!$C$49))<=2428.8,0,IF(MAX(0,AA27-Premissas!$C$50*MIN(AA27,Premissas!$C$49))<=2826.65,MAX(0,AA27-Premissas!$C$50*MIN(AA27,Premissas!$C$49))*0.075-182.16,IF(MAX(0,AA27-Premissas!$C$50*MIN(AA27,Premissas!$C$49))<=3751.05,MAX(0,AA27-Premissas!$C$50*MIN(AA27,Premissas!$C$49))*0.15-394.16,IF(MAX(0,AA27-Premissas!$C$50*MIN(AA27,Premissas!$C$49))<=4664.68,MAX(0,AA27-Premissas!$C$50*MIN(AA27,Premissas!$C$49))*0.225-675.49,MAX(0,AA27-Premissas!$C$50*MIN(AA27,Premissas!$C$49))*0.275-908.73))))-IF(AA27<=5000,312.89,IF(AA27<=7350,MAX(0,978.62-0.133145*AA27),0)))*Premissas!$C$48 -> 8250.7885 | AB29: =SUM(D29:O29) -> 0 | AC29: =SUM(P29:AA29) -> 34694.491 | AD29: =SUM(D29:AA29) -> 34694.491
B30: Custo da rota Anexo III (DAS + INSS + IRPF) | D30: =D24+D28+D29 -> 0 | E30: =E24+E28+E29 -> 0 | F30: =F24+F28+F29 -> 0 | G30: =G24+G28+G29 -> 1350 | H30: =H24+H28+H29 -> 2250 | I30: =I24+I28+I29 -> 2783.6 | J30: =J24+J28+J29 -> 3793 | K30: =K24+K28+K29 -> 5627 | ... AA30: =AA24+AA28+AA29 -> 59468.919 | AB30: =SUM(D30:O30) -> 54636.524 | AC30: =SUM(P30:AA30) -> 426471.4 | AD30: =SUM(D30:AA30) -> 481107.92
B31: Economia da rota Anexo III (positivo = compensa) | D31: =D20-D30 -> 0 | E31: =E20-E30 -> 0 | F31: =F20-F30 -> 0 | G31: =G20-G30 -> 2137.5 | H31: =H20-H30 -> 3562.5 | I31: =I20-I30 -> 4191.4 | J31: =J20-J30 -> 4532 | K31: =K20-K30 -> 5398 | ... AA31: =AA20-AA30 -> 1864.414 | AB31: =SUM(D31:O31) -> 48264.822 | AC31: =SUM(P31:AA31) -> 81139.461 | AD31: =SUM(D31:AA31) -> 129404.28
B33: Leitura da simulação | C33: ="Ano 1: "&IF(AB31>0,"pró-labore compensa (economia de R$ "&TEXT(AB31,"#,##0")&")","não compensa")&" · Ano 2: "&IF(AC31>0,"pró-labore compensa (economia de R$ "&TEXT(AC31,"#,##0")&")","não compensa (custaria R$ "&TEXT(-AC31,"#,##0")&" a mais)") -> Ano 1: pró-labore compensa (economia de R$ 48,265) · Ano 2: pró-labore compensa (economia de R$ 81,139)
B34: O pró-labore em si é pago aos próprios sócios; o custo comparado aqui é só o imposto. Decisão a validar com o contador, que também considera a tributação de lucros distribuídos.

Sheet DRE Mensal
B2: Demonstração do Resultado do Exercício — mês a mês
B3: Modelo do slide 11, em regime de competência: a receita e os custos entram no mês a que pertencem, não no mês em que o dinheiro se move.
B5: Conta | D5: M1 | E5: M2 | F5: M3 | G5: M4 | H5: M5 | I5: M6 | J5: M7 | K5: M8 | L5: M9 | M5: M10 | N5: M11 | O5: M12 | P5: M13 | Q5: M14 | R5: M15 | S5: M16 | T5: M17 | U5: M18 | V5: M19 | W5: M20 | X5: M21 | Y5: M22 | Z5: M23 | AA5: M24 | AB5: Ano 1 | AC5: Ano 2 | AD5: Total 24m
B6: Nº do mês | C6: 0 | D6: 1 | E6: 2 | F6: 3 | G6: 4 | H6: 5 | I6: 6 | J6: 7 | K6: 8 | L6: 9 | M6: 10 | N6: 11 | O6: 12 | P6: 13 | Q6: 14 | R6: 15 | S6: 16 | T6: 17 | U6: 18 | V6: 19 | W6: 20 | X6: 21 | Y6: 22 | Z6: 23 | AA6: 24
B7: 1. Receita total com vendas | D7: ='Receita e Clientes'!D15 -> 0 | E7: ='Receita e Clientes'!E15 -> 0 | F7: ='Receita e Clientes'!F15 -> 0 | G7: ='Receita e Clientes'!G15 -> 22500 | H7: ='Receita e Clientes'!H15 -> 37500 | I7: ='Receita e Clientes'!I15 -> 45000 | J7: ='Receita e Clientes'!J15 -> 52500 | K7: ='Receita e Clientes'!K15 -> 67500 | ... AA7: ='Receita e Clientes'!AA15 -> 300000 | AB7: =SUM(D7:O7) -> 615000 | AC7: =SUM(P7:AA7) -> 2610000 | AD7: =SUM(D7:AA7) -> 3225000
B8: 2. (−) Custos variáveis totais | D8: =D9+D10+D11+D12 -> 450 | E8: =E9+E10+E11+E12 -> 450 | F8: =F9+F10+F11+F12 -> 450 | G8: =G9+G10+G11+G12 -> 5296.5 | H8: =H9+H10+H11+H12 -> 8827.5 | I8: =I9+I10+I11+I12 -> 10593 | J8: =J9+J10+J11+J12 -> 12546 | K8: =K9+K10+K11+K12 -> 16452 | ... AA8: =AA9+AA10+AA11+AA12 -> 85453.333 | AB8: =SUM(D8:O8) -> 153697.35 | AC8: =SUM(P8:AA8) -> 717454.86 | AD8: =SUM(D8:AA8) -> 871152.2
B9: (−) custos diretos — processamento de IA | D9: ='Custos Variáveis'!D18 -> 450 | E9: ='Custos Variáveis'!E18 -> 450 | F9: ='Custos Variáveis'!F18 -> 450 | G9: ='Custos Variáveis'!G18 -> 450 | H9: ='Custos Variáveis'!H18 -> 750 | I9: ='Custos Variáveis'!I18 -> 900 | J9: ='Custos Variáveis'!J18 -> 1050 | K9: ='Custos Variáveis'!K18 -> 1350 | ... AA9: ='Custos Variáveis'!AA18 -> 6000 | AB9: =SUM(D9:O9) -> 13650 | AC9: =SUM(P9:AA9) -> 52200 | AD9: =SUM(D9:AA9) -> 65850
B10: (−) impostos sobre vendas (DAS) | D10: ='Custos Variáveis'!D19 -> 0 | E10: ='Custos Variáveis'!E19 -> 0 | F10: ='Custos Variáveis'!F19 -> 0 | G10: ='Custos Variáveis'!G19 -> 3487.5 | H10: ='Custos Variáveis'!H19 -> 5812.5 | I10: ='Custos Variáveis'!I19 -> 6975 | J10: ='Custos Variáveis'!J19 -> 8325 | K10: ='Custos Variáveis'!K19 -> 11025 | ... AA10: ='Custos Variáveis'!AA19 -> 61333.333 | AB10: =SUM(D10:O10) -> 102901.35 | AC10: =SUM(P10:AA10) -> 507610.86 | AD10: =SUM(D10:AA10) -> 610512.2
B11: (−) gastos com vendas (comissões e tarifas) | D11: ='Custos Variáveis'!D20+'Custos Variáveis'!D21 -> 0 | E11: ='Custos Variáveis'!E20+'Custos Variáveis'!E21 -> 0 | F11: ='Custos Variáveis'!F20+'Custos Variáveis'!F21 -> 0 | G11: ='Custos Variáveis'!G20+'Custos Variáveis'!G21 -> 1134 | H11: ='Custos Variáveis'!H20+'Custos Variáveis'!H21 -> 1890 | I11: ='Custos Variáveis'!I20+'Custos Variáveis'!I21 -> 2268 | J11: ='Custos Variáveis'!J20+'Custos Variáveis'!J21 -> 2646 | K11: ='Custos Variáveis'!K20+'Custos Variáveis'!K21 -> 3402 | ... AA11: ='Custos Variáveis'!AA20+'Custos Variáveis'!AA21 -> 15120 | AB11: =SUM(D11:O11) -> 30996 | AC11: =SUM(P11:AA11) -> 131544 | AD11: =SUM(D11:AA11) -> 162540
B12: (−) perdas com inadimplência | D12: ='Custos Variáveis'!D22 -> 0 | E12: ='Custos Variáveis'!E22 -> 0 | F12: ='Custos Variáveis'!F22 -> 0 | G12: ='Custos Variáveis'!G22 -> 225 | H12: ='Custos Variáveis'!H22 -> 375 | I12: ='Custos Variáveis'!I22 -> 450 | J12: ='Custos Variáveis'!J22 -> 525 | K12: ='Custos Variáveis'!K22 -> 675 | ... AA12: ='Custos Variáveis'!AA22 -> 3000 | AB12: =SUM(D12:O12) -> 6150 | AC12: =SUM(P12:AA12) -> 26100 | AD12: =SUM(D12:AA12) -> 32250
B13: 3. (=) Margem de contribuição (1 − 2) | D13: =D7-D8 -> -450 | E13: =E7-E8 -> -450 | F13: =F7-F8 -> -450 | G13: =G7-G8 -> 17203.5 | H13: =H7-H8 -> 28672.5 | I13: =I7-I8 -> 34407 | J13: =J7-J8 -> 39954 | K13: =K7-K8 -> 51048 | ... AA13: =AA7-AA8 -> 214546.67 | AB13: =SUM(D13:O13) -> 461302.65 | AC13: =SUM(P13:AA13) -> 1892545.1 | AD13: =SUM(D13:AA13) -> 2353847.8
B14: Margem de contribuição (% da receita) | D14: =IF(D7>0,D13/D7,0) -> 0 | E14: =IF(E7>0,E13/E7,0) -> 0 | F14: =IF(F7>0,F13/F7,0) -> 0 | G14: =IF(G7>0,G13/G7,0) -> 0.7646 | H14: =IF(H7>0,H13/H7,0) -> 0.7646 | I14: =IF(I7>0,I13/I7,0) -> 0.7646 | J14: =IF(J7>0,J13/J7,0) -> 0.76102857 | K14: =IF(K7>0,K13/K7,0) -> 0.75626667 | ... AD14: =IF(AD7>0,AD13/AD7,0) -> 0.72987529
B15: 4. (−) Custos fixos totais | D15: =D16+D17+D18+D19 -> 2601.6667 | E15: =E16+E17+E18+E19 -> 2601.6667 | F15: =F16+F17+F18+F19 -> 2601.6667 | G15: =G16+G17+G18+G19 -> 7101.6667 | H15: =H16+H17+H18+H19 -> 13101.667 | I15: =I16+I17+I18+I19 -> 10101.667 | J15: =J16+J17+J18+J19 -> 10101.667 | K15: =K16+K17+K18+K19 -> 13101.667 | ... AA15: =AA16+AA17+AA18+AA19 -> 25101.667 | AB15: =SUM(D15:O15) -> 131720 | AC15: =SUM(P15:AA15) -> 271220 | AD15: =SUM(D15:AA15) -> 402940
B16: mão de obra (salários + encargos) | D16: ='Custos Fixos'!D39 -> 0 | E16: ='Custos Fixos'!E39 -> 0 | F16: ='Custos Fixos'!F39 -> 0 | G16: ='Custos Fixos'!G39 -> 2600 | H16: ='Custos Fixos'!H39 -> 2600 | I16: ='Custos Fixos'!I39 -> 2600 | J16: ='Custos Fixos'!J39 -> 2600 | K16: ='Custos Fixos'!K39 -> 2600 | ... AA16: ='Custos Fixos'!AA39 -> 9750 | AB16: =SUM(D16:O16) -> 37050 | AC16: =SUM(P16:AA16) -> 101400 | AD16: =SUM(D16:AA16) -> 138450
B17: demais custos fixos (slide 7) | D17: ='Custos Fixos'!D40 -> 2500 | E17: ='Custos Fixos'!E40 -> 2500 | F17: ='Custos Fixos'!F40 -> 2500 | G17: ='Custos Fixos'!G40 -> 4400 | H17: ='Custos Fixos'!H40 -> 4400 | I17: ='Custos Fixos'!I40 -> 4400 | J17: ='Custos Fixos'!J40 -> 4400 | K17: ='Custos Fixos'!K40 -> 4400 | ... AA17: ='Custos Fixos'!AA40 -> 9250 | AB17: =SUM(D17:O17) -> 54450 | AC17: =SUM(P17:AA17) -> 96600 | AD17: =SUM(D17:AA17) -> 151050
B18: aquisição de clientes (verba comercial / CAC) | D18: ='Custos Variáveis'!D25 -> 0 | E18: ='Custos Variáveis'!E25 -> 0 | F18: ='Custos Variáveis'!F25 -> 0 | G18: ='Custos Variáveis'!G25 -> 0 | H18: ='Custos Variáveis'!H25 -> 6000 | I18: ='Custos Variáveis'!I25 -> 3000 | J18: ='Custos Variáveis'!J25 -> 3000 | K18: ='Custos Variáveis'!K25 -> 6000 | ... AA18: ='Custos Variáveis'!AA25 -> 6000 | AB18: =SUM(D18:O18) -> 39000 | AC18: =SUM(P18:AA18) -> 72000 | AD18: =SUM(D18:AA18) -> 111000
B19: depreciação e amortização | D19: ='Custos Fixos'!D41 -> 101.66667 | E19: ='Custos Fixos'!E41 -> 101.66667 | F19: ='Custos Fixos'!F41 -> 101.66667 | G19: ='Custos Fixos'!G41 -> 101.66667 | H19: ='Custos Fixos'!H41 -> 101.66667 | I19: ='Custos Fixos'!I41 -> 101.66667 | J19: ='Custos Fixos'!J41 -> 101.66667 | K19: ='Custos Fixos'!K41 -> 101.66667 | ... AA19: ='Custos Fixos'!AA41 -> 101.66667 | AB19: =SUM(D19:O19) -> 1220 | AC19: =SUM(P19:AA19) -> 1220 | AD19: =SUM(D19:AA19) -> 2440
B20: 5. (=) Resultado operacional (3 − 4) | D20: =D13-D15 -> -3051.6667 | E20: =E13-E15 -> -3051.6667 | F20: =F13-F15 -> -3051.6667 | G20: =G13-G15 -> 10101.833 | H20: =H13-H15 -> 15570.833 | I20: =I13-I15 -> 24305.333 | J20: =J13-J15 -> 29852.333 | K20: =K13-K15 -> 37946.333 | ... AA20: =AA13-AA15 -> 189445 | AB20: =SUM(D20:O20) -> 329582.65 | AC20: =SUM(P20:AA20) -> 1621325.1 | AD20: =SUM(D20:AA20) -> 1950907.8
B21: (+/−) resultado financeiro (rendimentos − tarifas bancárias) | D21: ='Fluxo de Caixa'!D11-Premissas!$C$43 -> 56 | E21: ='Fluxo de Caixa'!E11-Premissas!$C$43 -> 32.848 | F21: ='Fluxo de Caixa'!F11-Premissas!$C$43 -> 9.510784 | G21: ='Fluxo de Caixa'!G11-Premissas!$C$43 -> -14.01313 | H21: ='Fluxo de Caixa'!H11-Premissas!$C$43 -> -52.997235 | I21: ='Fluxo de Caixa'!I11-Premissas!$C$43 -> -22.241213 | J21: ='Fluxo de Caixa'!J11-Premissas!$C$43 -> 125.73686 | K21: ='Fluxo de Caixa'!K11-Premissas!$C$43 -> 320.77475 | ... AA21: ='Fluxo de Caixa'!AA11-Premissas!$C$43 -> 13148.603 | AB21: =SUM(D21:O21) -> 4648.0759 | AC21: =SUM(P21:AA21) -> 81740.733 | AD21: =SUM(D21:AA21) -> 86388.808
B22: (−) outras despesas (pré-operacionais, no M1) | D22: =IF(1=1,'Investimento Inicial'!$C$12,0) -> 5240 | E22: =IF(2=1,'Investimento Inicial'!$C$12,0) -> 0 | F22: =IF(3=1,'Investimento Inicial'!$C$12,0) -> 0 | G22: =IF(4=1,'Investimento Inicial'!$C$12,0) -> 0 | H22: =IF(5=1,'Investimento Inicial'!$C$12,0) -> 0 | I22: =IF(6=1,'Investimento Inicial'!$C$12,0) -> 0 | J22: =IF(7=1,'Investimento Inicial'!$C$12,0) -> 0 | K22: =IF(8=1,'Investimento Inicial'!$C$12,0) -> 0 | L22: =IF(9=1,'Investimento Inicial'!$C$12,0) -> 0 | M22: =IF(10=1,'Investimento Inicial'!$C$12,0) -> 0 | N22: =IF(11=1,'Investimento Inicial'!$C$12,0) -> 0 | O22: =IF(12=1,'Investimento Inicial'!$C$12,0) -> 0 | P22: =IF(13=1,'Investimento Inicial'!$C$12,0) -> 0 | Q22: =IF(14=1,'Investimento Inicial'!$C$12,0) -> 0 | R22: =IF(15=1,'Investimento Inicial'!$C$12,0) -> 0 | S22: =IF(16=1,'Investimento Inicial'!$C$12,0) -> 0 | T22: =IF(17=1,'Investimento Inicial'!$C$12,0) -> 0 | U22: =IF(18=1,'Investimento Inicial'!$C$12,0) -> 0 | V22: =IF(19=1,'Investimento Inicial'!$C$12,0) -> 0 | W22: =IF(20=1,'Investimento Inicial'!$C$12,0) -> 0 | X22: =IF(21=1,'Investimento Inicial'!$C$12,0) -> 0 | Y22: =IF(22=1,'Investimento Inicial'!$C$12,0) -> 0 | Z22: =IF(23=1,'Investimento Inicial'!$C$12,0) -> 0 | AA22: =IF(24=1,'Investimento Inicial'!$C$12,0) -> 0 | AB22: =SUM(D22:O22) -> 5240 | AC22: =SUM(P22:AA22) -> 0 | AD22: =SUM(D22:AA22) -> 5240
B23: (=) RESULTADO LÍQUIDO | D23: =D20+D21-D22 -> -8235.6667 | E23: =E20+E21-E22 -> -3018.8187 | F23: =F20+F21-F22 -> -3042.1559 | G23: =G20+G21-G22 -> 10087.82 | H23: =H20+H21-H22 -> 15517.836 | I23: =I20+I21-I22 -> 24283.092 | J23: =J20+J21-J22 -> 29978.07 | K23: =K20+K21-K22 -> 38267.108 | ... AA23: =AA20+AA21-AA22 -> 202593.6 | AB23: =SUM(D23:O23) -> 328990.73 | AC23: =SUM(P23:AA23) -> 1703065.9 | AD23: =SUM(D23:AA23) -> 2032056.6
B24: Margem líquida (% da receita) | D24: =IF(D7>0,D23/D7,0) -> 0 | E24: =IF(E7>0,E23/E7,0) -> 0 | F24: =IF(F7>0,F23/F7,0) -> 0 | G24: =IF(G7>0,G23/G7,0) -> 0.44834756 | H24: =IF(H7>0,H23/H7,0) -> 0.41380896 | I24: =IF(I7>0,I23/I7,0) -> 0.53962427 | J24: =IF(J7>0,J23/J7,0) -> 0.57101086 | K24: =IF(K7>0,K23/K7,0) -> 0.56692012 | ... AD24: =IF(AD7>0,AD23/AD7,0) -> 0.63009507
B25: Resultado líquido acumulado | D25: =N(C25)+D23 -> -8235.6667 | E25: =N(D25)+E23 -> -11254.485 | F25: =N(E25)+F23 -> -14296.641 | G25: =N(F25)+G23 -> -4208.821 | H25: =N(G25)+H23 -> 11309.015 | I25: =N(H25)+I23 -> 35592.107 | J25: =N(I25)+J23 -> 65570.177 | K25: =N(J25)+K23 -> 103837.29 | ... AA25: =N(Z25)+AA23 -> 2032056.6 | AB25: =O25 -> 328990.73 | AC25: =AA25 -> 2032056.6 | AD25: =AA25 -> 2032056.6
B26: Auxiliar: mês com resultado operacional ≥ 0 depois do piloto | D26: =IF(AND(D20>=0,1>=Premissas!$C$29),1,999) -> 999 | E26: =IF(AND(E20>=0,2>=Premissas!$C$29),2,999) -> 999 | F26: =IF(AND(F20>=0,3>=Premissas!$C$29),3,999) -> 999 | G26: =IF(AND(G20>=0,4>=Premissas!$C$29),4,999) -> 4 | H26: =IF(AND(H20>=0,5>=Premissas!$C$29),5,999) -> 5 | I26: =IF(AND(I20>=0,6>=Premissas!$C$29),6,999) -> 6 | J26: =IF(AND(J20>=0,7>=Premissas!$C$29),7,999) -> 7 | K26: =IF(AND(K20>=0,8>=Premissas!$C$29),8,999) -> 8 | L26: =IF(AND(L20>=0,9>=Premissas!$C$29),9,999) -> 9 | M26: =IF(AND(M20>=0,10>=Premissas!$C$29),10,999) -> 10 | N26: =IF(AND(N20>=0,11>=Premissas!$C$29),11,999) -> 11 | O26: =IF(AND(O20>=0,12>=Premissas!$C$29),12,999) -> 12 | P26: =IF(AND(P20>=0,13>=Premissas!$C$29),13,999) -> 13 | Q26: =IF(AND(Q20>=0,14>=Premissas!$C$29),14,999) -> 14 | R26: =IF(AND(R20>=0,15>=Premissas!$C$29),15,999) -> 15 | S26: =IF(AND(S20>=0,16>=Premissas!$C$29),16,999) -> 16 | T26: =IF(AND(T20>=0,17>=Premissas!$C$29),17,999) -> 17 | U26: =IF(AND(U20>=0,18>=Premissas!$C$29),18,999) -> 18 | V26: =IF(AND(V20>=0,19>=Premissas!$C$29),19,999) -> 19 | W26: =IF(AND(W20>=0,20>=Premissas!$C$29),20,999) -> 20 | X26: =IF(AND(X20>=0,21>=Premissas!$C$29),21,999) -> 21 | Y26: =IF(AND(Y20>=0,22>=Premissas!$C$29),22,999) -> 22 | Z26: =IF(AND(Z20>=0,23>=Premissas!$C$29),23,999) -> 23 | AA26: =IF(AND(AA20>=0,24>=Premissas!$C$29),24,999) -> 24

Sheet DRE Anual
B2: DRE — resultado operacional e resultado líquido
B3: Exatamente o formato do slide 11, com R$ e % da receita (análise vertical) para o Ano 1, o Ano 2 e os 24 meses.
C5: Ano 1 (R$) | D5: % | E5: Ano 2 (R$) | F5: % | G5: 24 meses (R$) | H5: % | I5: Ano 2 / Ano 1
B6: 1. Receita total com vendas (à vista + a prazo) | C6: ='DRE Mensal'!AB7 -> 615000 | D6: =IF(C$6<>0,C6/C$6,0) -> 1 | E6: ='DRE Mensal'!AC7 -> 2610000 | F6: =IF(E$6<>0,E6/E$6,0) -> 1 | G6: ='DRE Mensal'!AD7 -> 3225000 | H6: =IF(G$6<>0,G6/G$6,0) -> 1 | I6: =IF(C6<>0,E6/C6-1,0) -> 3.2439024
B7: 2. Custos variáveis totais | C7: ='DRE Mensal'!AB8 -> 153697.35 | D7: =IF(C$6<>0,C7/C$6,0) -> 0.24991438 | E7: ='DRE Mensal'!AC8 -> 717454.86 | F7: =IF(E$6<>0,E7/E$6,0) -> 0.27488692 | G7: ='DRE Mensal'!AD8 -> 871152.2 | H7: =IF(G$6<>0,G7/G$6,0) -> 0.27012471 | I7: =IF(C7<>0,E7/C7-1,0) -> 3.6679717
B8: (−) custos diretos (processamento de IA) | C8: ='DRE Mensal'!AB9 -> 13650 | D8: =IF(C$6<>0,C8/C$6,0) -> 0.022195122 | E8: ='DRE Mensal'!AC9 -> 52200 | F8: =IF(E$6<>0,E8/E$6,0) -> 0.02 | G8: ='DRE Mensal'!AD9 -> 65850 | H8: =IF(G$6<>0,G8/G$6,0) -> 0.020418605 | I8: =IF(C8<>0,E8/C8-1,0) -> 2.8241758
B9: (−) impostos sobre vendas (DAS) | C9: ='DRE Mensal'!AB10 -> 102901.35 | D9: =IF(C$6<>0,C9/C$6,0) -> 0.16731926 | E9: ='DRE Mensal'!AC10 -> 507610.86 | F9: =IF(E$6<>0,E9/E$6,0) -> 0.19448692 | G9: ='DRE Mensal'!AD10 -> 610512.2 | H9: =IF(G$6<>0,G9/G$6,0) -> 0.18930611 | I9: =IF(C9<>0,E9/C9-1,0) -> 3.9329856
B10: (−) gastos com vendas (comissões, tarifas de cobrança) | C10: ='DRE Mensal'!AB11 -> 30996 | D10: =IF(C$6<>0,C10/C$6,0) -> 0.0504 | E10: ='DRE Mensal'!AC11 -> 131544 | F10: =IF(E$6<>0,E10/E$6,0) -> 0.0504 | G10: ='DRE Mensal'!AD11 -> 162540 | H10: =IF(G$6<>0,G10/G$6,0) -> 0.0504 | I10: =IF(C10<>0,E10/C10-1,0) -> 3.2439024
B11: (−) perdas com inadimplência | C11: ='DRE Mensal'!AB12 -> 6150 | D11: =IF(C$6<>0,C11/C$6,0) -> 0.01 | E11: ='DRE Mensal'!AC12 -> 26100 | F11: =IF(E$6<>0,E11/E$6,0) -> 0.01 | G11: ='DRE Mensal'!AD12 -> 32250 | H11: =IF(G$6<>0,G11/G$6,0) -> 0.01 | I11: =IF(C11<>0,E11/C11-1,0) -> 3.2439024
B12: 3. (=) Margem de contribuição (1 − 2) | C12: ='DRE Mensal'!AB13 -> 461302.65 | D12: =IF(C$6<>0,C12/C$6,0) -> 0.75008562 | E12: ='DRE Mensal'!AC13 -> 1892545.1 | F12: =IF(E$6<>0,E12/E$6,0) -> 0.72511308 | G12: ='DRE Mensal'!AD13 -> 2353847.8 | H12: =IF(G$6<>0,G12/G$6,0) -> 0.72987529 | I12: =IF(C12<>0,E12/C12-1,0) -> 3.1026106
B13: 4. (−) Custos fixos totais | C13: ='DRE Mensal'!AB15 -> 131720 | D13: =IF(C$6<>0,C13/C$6,0) -> 0.21417886 | E13: ='DRE Mensal'!AC15 -> 271220 | F13: =IF(E$6<>0,E13/E$6,0) -> 0.10391571 | G13: ='DRE Mensal'!AD15 -> 402940 | H13: =IF(G$6<>0,G13/G$6,0) -> 0.12494264 | I13: =IF(C13<>0,E13/C13-1,0) -> 1.0590647
B14: mão de obra | C14: ='DRE Mensal'!AB16 -> 37050 | D14: =IF(C$6<>0,C14/C$6,0) -> 0.060243902 | E14: ='DRE Mensal'!AC16 -> 101400 | F14: =IF(E$6<>0,E14/E$6,0) -> 0.038850575 | G14: ='DRE Mensal'!AD16 -> 138450 | H14: =IF(G$6<>0,G14/G$6,0) -> 0.042930233 | I14: =IF(C14<>0,E14/C14-1,0) -> 1.7368421
B15: demais custos fixos | C15: ='DRE Mensal'!AB17 -> 54450 | D15: =IF(C$6<>0,C15/C$6,0) -> 0.088536585 | E15: ='DRE Mensal'!AC17 -> 96600 | F15: =IF(E$6<>0,E15/E$6,0) -> 0.037011494 | G15: ='DRE Mensal'!AD17 -> 151050 | H15: =IF(G$6<>0,G15/G$6,0) -> 0.046837209 | I15: =IF(C15<>0,E15/C15-1,0) -> 0.77410468
B16: aquisição de clientes (CAC) | C16: ='DRE Mensal'!AB18 -> 39000 | D16: =IF(C$6<>0,C16/C$6,0) -> 0.063414634 | E16: ='DRE Mensal'!AC18 -> 72000 | F16: =IF(E$6<>0,E16/E$6,0) -> 0.027586207 | G16: ='DRE Mensal'!AD18 -> 111000 | H16: =IF(G$6<>0,G16/G$6,0) -> 0.034418605 | I16: =IF(C16<>0,E16/C16-1,0) -> 0.84615385
B17: depreciação e amortização | C17: ='DRE Mensal'!AB19 -> 1220 | D17: =IF(C$6<>0,C17/C$6,0) -> 0.0019837398 | E17: ='DRE Mensal'!AC19 -> 1220 | F17: =IF(E$6<>0,E17/E$6,0) -> 0.00046743295 | G17: ='DRE Mensal'!AD19 -> 2440 | H17: =IF(G$6<>0,G17/G$6,0) -> 0.00075658915 | I17: =IF(C17<>0,E17/C17-1,0) -> 0
B18: 5. Resultado operacional (lucro/prejuízo) (3 − 4) | C18: ='DRE Mensal'!AB20 -> 329582.65 | D18: =IF(C$6<>0,C18/C$6,0) -> 0.53590675 | E18: ='DRE Mensal'!AC20 -> 1621325.1 | F18: =IF(E$6<>0,E18/E$6,0) -> 0.62119737 | G18: ='DRE Mensal'!AD20 -> 1950907.8 | H18: =IF(G$6<>0,G18/G$6,0) -> 0.60493265 | I18: =IF(C18<>0,E18/C18-1,0) -> 3.9193279
B19: (+/−) resultado financeiro | C19: ='DRE Mensal'!AB21 -> 4648.0759 | D19: =IF(C$6<>0,C19/C$6,0) -> 0.007557847 | E19: ='DRE Mensal'!AC21 -> 81740.733 | F19: =IF(E$6<>0,E19/E$6,0) -> 0.031318288 | G19: ='DRE Mensal'!AD21 -> 86388.808 | H19: =IF(G$6<>0,G19/G$6,0) -> 0.026787227 | I19: =IF(C19<>0,E19/C19-1,0) -> 16.585929
B20: (−) outras despesas | C20: ='DRE Mensal'!AB22 -> 5240 | D20: =IF(C$6<>0,C20/C$6,0) -> 0.0085203252 | E20: ='DRE Mensal'!AC22 -> 0 | F20: =IF(E$6<>0,E20/E$6,0) -> 0 | G20: ='DRE Mensal'!AD22 -> 5240 | H20: =IF(G$6<>0,G20/G$6,0) -> 0.0016248062 | I20: =IF(C20<>0,E20/C20-1,0) -> -1
B21: (=) RESULTADO LÍQUIDO | C21: ='DRE Mensal'!AB23 -> 328990.73 | D21: =IF(C$6<>0,C21/C$6,0) -> 0.53494428 | E21: ='DRE Mensal'!AC23 -> 1703065.9 | F21: =IF(E$6<>0,E21/E$6,0) -> 0.65251566 | G21: ='DRE Mensal'!AD23 -> 2032056.6 | H21: =IF(G$6<>0,G21/G$6,0) -> 0.63009507 | I21: =IF(C21<>0,E21/C21-1,0) -> 4.1766379
B23: Como ler: a margem de contribuição mostra quanto de cada R$ 100 vendidos sobra para pagar os custos fixos. O DAS cresce no Ano 2 porque a alíquota efetiva sobe junto com a receita dos últimos 12 meses.
B25: Dados do gráfico | C25: Ano 1 | E25: Ano 2
B26: Receita | C26: =C6 -> 615000 | E26: =E6 -> 2610000
B27: Custos variáveis | C27: =C7 -> 153697.35 | E27: =E7 -> 717454.86
B28: Margem de contribuição | C28: =C12 -> 461302.65 | E28: =E12 -> 1892545.1
B29: Custos fixos | C29: =C13 -> 131720 | E29: =E13 -> 271220
B30: Resultado líquido | C30: =C21 -> 328990.73 | E30: =E21 -> 1703065.9

Sheet Fluxo de Caixa
B2: Fluxo de caixa (regime de caixa)
B3: Modelo do slide 13. Cada valor entra no mês em que o dinheiro efetivamente entra ou sai: vendas recebidas em 30 dias; salários, DAS e comissões pagos no mês seguinte.
B5: Linha | C5: M0 (pré) | D5: M1 | E5: M2 | F5: M3 | G5: M4 | H5: M5 | I5: M6 | J5: M7 | K5: M8 | L5: M9 | M5: M10 | N5: M11 | O5: M12 | P5: M13 | Q5: M14 | R5: M15 | S5: M16 | T5: M17 | U5: M18 | V5: M19 | W5: M20 | X5: M21 | Y5: M22 | Z5: M23 | AA5: M24 | AB5: Ano 1 | AC5: Ano 2 | AD5: Total 24m
B6: Nº do mês | C6: 0 | D6: 1 | E6: 2 | F6: 3 | G6: 4 | H6: 5 | I6: 6 | J6: 7 | K6: 8 | L6: 9 | M6: 10 | N6: 11 | O6: 12 | P6: 13 | Q6: 14 | R6: 15 | S6: 16 | T6: 17 | U6: 18 | V6: 19 | W6: 20 | X6: 21 | Y6: 22 | Z6: 23 | AA6: 24
B7: Saldo inicial | C7: 0 | D7: =C24 -> 14500 | E7: =D24 -> 11606 | F7: =E24 -> 8688.848 | G7: =F24 -> 5748.3588 | H7: =G24 -> 875.34565 | I7: =H24 -> 4719.8484 | J7: =I24 -> 23217.107 | K7: =J24 -> 47596.844 | ... AA7: =Z24 -> 1651075.3 | AB7: =C7 -> 0 | AC7: =P7 -> 265500.73 | AD7: =C7 -> 0
B8: ENTRADAS
B9: Aporte dos sócios | C9: ='Investimento Inicial'!$C$35 -> 25840 | D9: 0 | E9: 0 | F9: 0 | G9: 0 | H9: 0 | I9: 0 | J9: 0 | K9: 0 | L9: 0 | M9: 0 | N9: 0 | O9: 0 | P9: 0 | Q9: 0 | R9: 0 | S9: 0 | T9: 0 | U9: 0 | V9: 0 | W9: 0 | X9: 0 | Y9: 0 | Z9: 0 | AA9: 0 | AB9: =SUM(C9:O9) -> 25840 | AC9: =SUM(P9:AA9) -> 0 | AD9: =SUM(C9:AA9) -> 25840
B10: Recebimento de clientes (faturas do mês anterior) | C10: 0 | D10: =0 -> 0 | E10: ='Receita e Clientes'!D15*(1-Premissas!$C$40) -> 0 | F10: ='Receita e Clientes'!E15*(1-Premissas!$C$40) -> 0 | G10: ='Receita e Clientes'!F15*(1-Premissas!$C$40) -> 0 | H10: ='Receita e Clientes'!G15*(1-Premissas!$C$40) -> 22275 | I10: ='Receita e Clientes'!H15*(1-Premissas!$C$40) -> 37125 | J10: ='Receita e Clientes'!I15*(1-Premissas!$C$40) -> 44550 | K10: ='Receita e Clientes'!J15*(1-Premissas!$C$40) -> 51975 | L10: ='Receita e Clientes'!K15*(1-Premissas!$C$40) -> 66825 | ... AA10: ='Receita e Clientes'!Z15*(1-Premissas!$C$40) -> 282150 | AB10: =SUM(C10:O10) -> 490050 | AC10: =SUM(P10:AA10) -> 2405700 | AD10: =SUM(C10:AA10) -> 2895750
B11: Rendimento do caixa aplicado | C11: 0 | D11: =MAX(0,D7)*Premissas!$C$44 -> 116 | E11: =MAX(0,E7)*Premissas!$C$44 -> 92.848 | F11: =MAX(0,F7)*Premissas!$C$44 -> 69.510784 | G11: =MAX(0,G7)*Premissas!$C$44 -> 45.98687 | H11: =MAX(0,H7)*Premissas!$C$44 -> 7.0027652 | I11: =MAX(0,I7)*Premissas!$C$44 -> 37.758787 | J11: =MAX(0,J7)*Premissas!$C$44 -> 185.73686 | K11: =MAX(0,K7)*Premissas!$C$44 -> 380.77475 | ... AA11: =MAX(0,AA7)*Premissas!$C$44 -> 13208.603 | AB11: =SUM(C11:O11) -> 5368.0759 | AC11: =SUM(P11:AA11) -> 82460.733 | AD11: =SUM(C11:AA11) -> 87828.808
B12: Total de entradas | C12: =SUM(C9:C11) -> 25840 | D12: =SUM(D9:D11) -> 116 | E12: =SUM(E9:E11) -> 92.848 | F12: =SUM(F9:F11) -> 69.510784 | G12: =SUM(G9:G11) -> 45.98687 | H12: =SUM(H9:H11) -> 22282.003 | I12: =SUM(I9:I11) -> 37162.759 | J12: =SUM(J9:J11) -> 44735.737 | ... AA12: =SUM(AA9:AA11) -> 295358.6 | AB12: =SUM(C12:O12) -> 521258.08 | AC12: =SUM(P12:AA12) -> 2488160.7 | AD12: =SUM(C12:AA12) -> 3009418.8
B13: SAÍDAS
B14: Investimentos (pré-operacionais + fixos) | C14: ='Investimento Inicial'!$C$12+'Investimento Inicial'!$C$19 -> 11340 | D14: 0 | E14: 0 | F14: 0 | G14: 0 | H14: 0 | I14: 0 | J14: 0 | K14: 0 | L14: 0 | M14: 0 | N14: 0 | O14: 0 | P14: 0 | Q14: 0 | R14: 0 | S14: 0 | T14: 0 | U14: 0 | V14: 0 | W14: 0 | X14: 0 | Y14: 0 | Z14: 0 | AA14: 0 | AB14: =SUM(C14:O14) -> 11340 | AC14: =SUM(P14:AA14) -> 0 | AD14: =SUM(C14:AA14) -> 11340
B15: Salários e encargos (pagos no mês seguinte) | C15: 0 | D15: =0 -> 0 | E15: ='Custos Fixos'!D39 -> 0 | F15: ='Custos Fixos'!E39 -> 0 | G15: ='Custos Fixos'!F39 -> 0 | H15: ='Custos Fixos'!G39 -> 2600 | I15: ='Custos Fixos'!H39 -> 2600 | J15: ='Custos Fixos'!I39 -> 2600 | K15: ='Custos Fixos'!J39 -> 2600 | L15: ='Custos Fixos'!K39 -> 2600 | ... AA15: ='Custos Fixos'!Z39 -> 9750 | AB15: =SUM(C15:O15) -> 29900 | AC15: =SUM(P15:AA15) -> 98800 | AD15: =SUM(C15:AA15) -> 128700
B16: Demais custos fixos | C16: 0 | D16: ='Custos Fixos'!D40 -> 2500 | E16: ='Custos Fixos'!E40 -> 2500 | F16: ='Custos Fixos'!F40 -> 2500 | G16: ='Custos Fixos'!G40 -> 4400 | H16: ='Custos Fixos'!H40 -> 4400 | I16: ='Custos Fixos'!I40 -> 4400 | J16: ='Custos Fixos'!J40 -> 4400 | K16: ='Custos Fixos'!K40 -> 4400 | ... AA16: ='Custos Fixos'!AA40 -> 9250 | AB16: =SUM(C16:O16) -> 54450 | AC16: =SUM(P16:AA16) -> 96600 | AD16: =SUM(C16:AA16) -> 151050
B17: Processamento de IA | C17: 0 | D17: ='Custos Variáveis'!D18 -> 450 | E17: ='Custos Variáveis'!E18 -> 450 | F17: ='Custos Variáveis'!F18 -> 450 | G17: ='Custos Variáveis'!G18 -> 450 | H17: ='Custos Variáveis'!H18 -> 750 | I17: ='Custos Variáveis'!I18 -> 900 | J17: ='Custos Variáveis'!J18 -> 1050 | K17: ='Custos Variáveis'!K18 -> 1350 | ... AA17: ='Custos Variáveis'!AA18 -> 6000 | AB17: =SUM(C17:O17) -> 13650 | AC17: =SUM(P17:AA17) -> 52200 | AD17: =SUM(C17:AA17) -> 65850
B18: Aquisição de clientes (CAC) | C18: 0 | D18: ='Custos Variáveis'!D25 -> 0 | E18: ='Custos Variáveis'!E25 -> 0 | F18: ='Custos Variáveis'!F25 -> 0 | G18: ='Custos Variáveis'!G25 -> 0 | H18: ='Custos Variáveis'!H25 -> 6000 | I18: ='Custos Variáveis'!I25 -> 3000 | J18: ='Custos Variáveis'!J25 -> 3000 | K18: ='Custos Variáveis'!K25 -> 6000 | ... AA18: ='Custos Variáveis'!AA25 -> 6000 | AB18: =SUM(C18:O18) -> 39000 | AC18: =SUM(P18:AA18) -> 72000 | AD18: =SUM(C18:AA18) -> 111000
B19: DAS (vence no mês seguinte) | C19: 0 | D19: =0 -> 0 | E19: ='Custos Variáveis'!D19 -> 0 | F19: ='Custos Variáveis'!E19 -> 0 | G19: ='Custos Variáveis'!F19 -> 0 | H19: ='Custos Variáveis'!G19 -> 3487.5 | I19: ='Custos Variáveis'!H19 -> 5812.5 | J19: ='Custos Variáveis'!I19 -> 6975 | K19: ='Custos Variáveis'!J19 -> 8325 | L19: ='Custos Variáveis'!K19 -> 11025 | ... AA19: ='Custos Variáveis'!Z19 -> 57684 | AB19: =SUM(C19:O19) -> 81701.346 | AC19: =SUM(P19:AA19) -> 467477.52 | AD19: =SUM(C19:AA19) -> 549178.87
B20: Comissões (pagas no mês seguinte) | C20: 0 | D20: =0 -> 0 | E20: ='Custos Variáveis'!D20 -> 0 | F20: ='Custos Variáveis'!E20 -> 0 | G20: ='Custos Variáveis'!F20 -> 0 | H20: ='Custos Variáveis'!G20 -> 1125 | I20: ='Custos Variáveis'!H20 -> 1875 | J20: ='Custos Variáveis'!I20 -> 2250 | K20: ='Custos Variáveis'!J20 -> 2625 | L20: ='Custos Variáveis'!K20 -> 3375 | ... AA20: ='Custos Variáveis'!Z20 -> 14250 | AB20: =SUM(C20:O20) -> 24750 | AC20: =SUM(P20:AA20) -> 121500 | AD20: =SUM(C20:AA20) -> 146250
B21: Tarifas de cobrança e bancárias | C21: 0 | D21: ='Custos Variáveis'!D21+Premissas!$C$43 -> 60 | E21: ='Custos Variáveis'!E21+Premissas!$C$43 -> 60 | F21: ='Custos Variáveis'!F21+Premissas!$C$43 -> 60 | G21: ='Custos Variáveis'!G21+Premissas!$C$43 -> 69 | H21: ='Custos Variáveis'!H21+Premissas!$C$43 -> 75 | I21: ='Custos Variáveis'!I21+Premissas!$C$43 -> 78 | J21: ='Custos Variáveis'!J21+Premissas!$C$43 -> 81 | K21: ='Custos Variáveis'!K21+Premissas!$C$43 -> 87 | ... AA21: ='Custos Variáveis'!AA21+Premissas!$C$43 -> 180 | AB21: =SUM(C21:O21) -> 966 | AC21: =SUM(P21:AA21) -> 1764 | AD21: =SUM(C21:AA21) -> 2730
B22: Total de saídas | C22: =SUM(C14:C21) -> 11340 | D22: =SUM(D14:D21) -> 3010 | E22: =SUM(E14:E21) -> 3010 | F22: =SUM(F14:F21) -> 3010 | G22: =SUM(G14:G21) -> 4919 | H22: =SUM(H14:H21) -> 18437.5 | I22: =SUM(I14:I21) -> 18665.5 | J22: =SUM(J14:J21) -> 20356 | ... AA22: =SUM(AA14:AA21) -> 103114 | AB22: =SUM(C22:O22) -> 255757.35 | AC22: =SUM(P22:AA22) -> 910341.52 | AD22: =SUM(C22:AA22) -> 1166098.9
B23: Resultado de caixa do mês (entradas − saídas) | C23: =C12-C22 -> 14500 | D23: =D12-D22 -> -2894 | E23: =E12-E22 -> -2917.152 | F23: =F12-F22 -> -2940.4892 | G23: =G12-G22 -> -4873.0131 | H23: =H12-H22 -> 3844.5028 | I23: =I12-I22 -> 18497.259 | J23: =J12-J22 -> 24379.737 | ... AA23: =AA12-AA22 -> 192244.6 | AB23: =SUM(C23:O23) -> 265500.73 | AC23: =SUM(P23:AA23) -> 1577819.2 | AD23: =SUM(C23:AA23) -> 1843319.9
B24: SALDO FINAL DE CAIXA | C24: =C7+C23 -> 14500 | D24: =D7+D23 -> 11606 | E24: =E7+E23 -> 8688.848 | F24: =F7+F23 -> 5748.3588 | G24: =G7+G23 -> 875.34565 | H24: =H7+H23 -> 4719.8484 | I24: =I7+I23 -> 23217.107 | J24: =J7+J23 -> 47596.844 | ... AA24: =AA7+AA23 -> 1843319.9 | AB24: =O24 -> 265500.73 | AC24: =AA24 -> 1843319.9 | AD24: =AA24 -> 1843319.9
B26: Saldo ficou negativo em algum mês? | C26: =IF(MIN(C24:AA24)<0,"SIM — aumentar o aporte","NÃO — o investimento inicial cobre a operação") -> NÃO — o investimento inicial cobre a operação
B27: Auxiliar: mês em que o saldo recupera o aporte | D27: =IF(D24>=C9,1,999) -> 999 | E27: =IF(E24>=C9,2,999) -> 999 | F27: =IF(F24>=C9,3,999) -> 999 | G27: =IF(G24>=C9,4,999) -> 999 | H27: =IF(H24>=C9,5,999) -> 999 | I27: =IF(I24>=C9,6,999) -> 999 | J27: =IF(J24>=C9,7,999) -> 7 | K27: =IF(K24>=C9,8,999) -> 8 | L27: =IF(L24>=C9,9,999) -> 9 | M27: =IF(M24>=C9,10,999) -> 10 | N27: =IF(N24>=C9,11,999) -> 11 | O27: =IF(O24>=C9,12,999) -> 12 | P27: =IF(P24>=C9,13,999) -> 13 | Q27: =IF(Q24>=C9,14,999) -> 14 | R27: =IF(R24>=C9,15,999) -> 15 | S27: =IF(S24>=C9,16,999) -> 16 | T27: =IF(T24>=C9,17,999) -> 17 | U27: =IF(U24>=C9,18,999) -> 18 | V27: =IF(V24>=C9,19,999) -> 19 | W27: =IF(W24>=C9,20,999) -> 20 | X27: =IF(X24>=C9,21,999) -> 21 | Y27: =IF(Y24>=C9,22,999) -> 22 | Z27: =IF(Z24>=C9,23,999) -> 23 | AA27: =IF(AA24>=C9,24,999) -> 24

Sheet DRE x Caixa
B2: Comparativo: DRE × fluxo de caixa
B3: Slide 14. A DRE mede o desempenho econômico (lucro, competência); o fluxo de caixa mede o financeiro (saldo, caixa).
B5: Linha | C5: M0 (pré) | D5: M1 | E5: M2 | F5: M3 | G5: M4 | H5: M5 | I5: M6 | J5: M7 | K5: M8 | L5: M9 | M5: M10 | N5: M11 | O5: M12 | P5: M13 | Q5: M14 | R5: M15 | S5: M16 | T5: M17 | U5: M18 | V5: M19 | W5: M20 | X5: M21 | Y5: M22 | Z5: M23 | AA5: M24 | AB5: Ano 1 | AC5: Ano 2 | AD5: Total 24m
B6: Nº do mês | C6: 0 | D6: 1 | E6: 2 | F6: 3 | G6: 4 | H6: 5 | I6: 6 | J6: 7 | K6: 8 | L6: 9 | M6: 10 | N6: 11 | O6: 12 | P6: 13 | Q6: 14 | R6: 15 | S6: 16 | T6: 17 | U6: 18 | V6: 19 | W6: 20 | X6: 21 | Y6: 22 | Z6: 23 | AA6: 24
B7: Resultado líquido do mês (DRE) | C7: 0 | D7: ='DRE Mensal'!D23 -> -8235.6667 | E7: ='DRE Mensal'!E23 -> -3018.8187 | F7: ='DRE Mensal'!F23 -> -3042.1559 | G7: ='DRE Mensal'!G23 -> 10087.82 | H7: ='DRE Mensal'!H23 -> 15517.836 | I7: ='DRE Mensal'!I23 -> 24283.092 | J7: ='DRE Mensal'!J23 -> 29978.07 | K7: ='DRE Mensal'!K23 -> 38267.108 | ... AA7: ='DRE Mensal'!AA23 -> 202593.6 | AB7: =SUM(C7:O7) -> 328990.73 | AC7: =SUM(P7:AA7) -> 1703065.9 | AD7: =SUM(C7:AA7) -> 2032056.6
B8: Resultado de caixa do mês, sem o aporte (fluxo) | C8: ='Fluxo de Caixa'!C23-'Fluxo de Caixa'!C9 -> -11340 | D8: ='Fluxo de Caixa'!D23-'Fluxo de Caixa'!D9 -> -2894 | E8: ='Fluxo de Caixa'!E23-'Fluxo de Caixa'!E9 -> -2917.152 | F8: ='Fluxo de Caixa'!F23-'Fluxo de Caixa'!F9 -> -2940.4892 | G8: ='Fluxo de Caixa'!G23-'Fluxo de Caixa'!G9 -> -4873.0131 | H8: ='Fluxo de Caixa'!H23-'Fluxo de Caixa'!H9 -> 3844.5028 | I8: ='Fluxo de Caixa'!I23-'Fluxo de Caixa'!I9 -> 18497.259 | J8: ='Fluxo de Caixa'!J23-'Fluxo de Caixa'!J9 -> 24379.737 | ... AA8: ='Fluxo de Caixa'!AA23-'Fluxo de Caixa'!AA9 -> 192244.6 | AB8: =SUM(C8:O8) -> 239660.73 | AC8: =SUM(P8:AA8) -> 1577819.2 | AD8: =SUM(C8:AA8) -> 1817479.9
B9: Diferença (caixa − lucro) | C9: =C8-C7 -> -11340 | D9: =D8-D7 -> 5341.6667 | E9: =E8-E7 -> 101.66667 | F9: =F8-F7 -> 101.66667 | G9: =G8-G7 -> -14960.833 | H9: =H8-H7 -> -11673.333 | I9: =I8-I7 -> -5785.8333 | J9: =J8-J7 -> -5598.3333 | ... AA9: =AA8-AA7 -> -10349 | AB9: =SUM(C9:O9) -> -89330 | AC9: =SUM(P9:AA9) -> -125246.67 | AD9: =SUM(C9:AA9) -> -214576.67
B11: Lucro acumulado (DRE) | C11: =C7 -> 0 | D11: =C11+D7 -> -8235.6667 | E11: =D11+E7 -> -11254.485 | F11: =E11+F7 -> -14296.641 | G11: =F11+G7 -> -4208.821 | H11: =G11+H7 -> 11309.015 | I11: =H11+I7 -> 35592.107 | J11: =I11+J7 -> 65570.177 | K11: =J11+K7 -> 103837.29 | ... AA11: =Z11+AA7 -> 2032056.6 | AB11: =O11 -> 328990.73 | AC11: =AA11 -> 2032056.6 | AD11: =AA11 -> 2032056.6
B12: Caixa gerado acumulado (fluxo, sem aporte) | C12: =C8 -> -11340 | D12: =C12+D8 -> -14234 | E12: =D12+E8 -> -17151.152 | F12: =E12+F8 -> -20091.641 | G12: =F12+G8 -> -24964.654 | H12: =G12+H8 -> -21120.152 | I12: =H12+I8 -> -2622.8928 | J12: =I12+J8 -> 21756.844 | K12: =J12+K8 -> 48725.619 | ... AA12: =Z12+AA8 -> 1817479.9 | AB12: =O12 -> 239660.73 | AC12: =AA12 -> 1817479.9 | AD12: =AA12 -> 1817479.9
B14: Por que os dois números são diferentes
B15: • Prazo de recebimento: a receita entra na DRE no mês da venda, mas o dinheiro só chega 30 dias depois (o caixa fica "atrás" da DRE quando as vendas crescem).
B16: • Prazo de pagamento: salários, DAS e comissões aparecem na DRE do mês, mas saem do caixa no mês seguinte (isso alivia o caixa).
B17: • Depreciação: reduz o lucro todo mês, mas não é saída de dinheiro; a compra do equipamento saiu inteira do caixa no M0.
B18: • Despesas pré-operacionais: pagas no M0 (caixa) e lançadas na DRE do M1.
B19: • Inadimplência: a DRE registra a perda, o caixa simplesmente não recebe.

Sheet Indicadores
B2: Indicadores de resultado
B3: Slide 15 (rentabilidade, ponto de equilíbrio, margem de contribuição) e indicadores de SaaS.
B5: Indicador | C5: Ano 1 | D5: Ano 2 | E5: 24 meses | F5: Fórmula / leitura
B6: Investimento e retorno
B7: Investimento inicial total | C7: ='Investimento Inicial'!$C$31 -> 25840 | F7: Aba Investimento Inicial (slide 6).
B8: Receita | C8: ='DRE Anual'!C6 -> 615000 | D8: ='DRE Anual'!E6 -> 2610000 | E8: ='DRE Anual'!G6 -> 3225000 | F8: DRE Anual.
B9: Resultado líquido (lucro) | C9: ='DRE Anual'!C21 -> 328990.73 | D9: ='DRE Anual'!E21 -> 1703065.9 | E9: ='DRE Anual'!G21 -> 2032056.6 | F9: DRE Anual.
B10: Rentabilidade = lucro ÷ investimento inicial × 100 | C10: =C9/$C$7 -> 12.731839 | D10: =D9/$C$7 -> 65.908122 | E10: =E9/$C$7 -> 78.639961 | F10: Fórmula do slide 15. Fica muito alta porque um SaaS exige pouco investimento fixo; o risco está no tempo e no esforço dos sócios, que não entram no investimento.
B11: Lucratividade = lucro ÷ receita | C11: =IF(C8>0,C9/C8,0) -> 0.53494428 | D11: =IF(D8>0,D9/D8,0) -> 0.65251566 | E11: =IF(E8>0,E9/E8,0) -> 0.63009507 | F11: Quanto de cada R$ 100 vendidos vira lucro.
B12: Prazo de retorno do investimento (mês) | C12: =IF(MIN('Fluxo de Caixa'!D27:AA27)>24,"após o M24",MIN('Fluxo de Caixa'!D27:AA27)) -> 7 | F12: Primeiro mês em que o saldo de caixa volta a ser igual ou maior que o aporte dos sócios.
B13: Margem de contribuição e ponto de equilíbrio
B14: Margem de contribuição (R$) | C14: ='DRE Anual'!C12 -> 461302.65 | D14: ='DRE Anual'!E12 -> 1892545.1 | E14: ='DRE Anual'!G12 -> 2353847.8 | F14: Receita − custos variáveis (slide 15).
B15: Margem de contribuição (% da receita) | C15: =IF(C8>0,C14/C8,0) -> 0.75008562 | D15: =IF(D8>0,D14/D8,0) -> 0.72511308 | E15: =IF(E8>0,E14/E8,0) -> 0.72987529 | F15: Índice usado no ponto de equilíbrio.
B16: Custos fixos totais do período | C16: ='DRE Anual'!C13 -> 131720 | D16: ='DRE Anual'!E13 -> 271220 | E16: ='DRE Anual'!G13 -> 402940 | F16: Inclui a verba de aquisição de clientes e a depreciação.
B17: Ponto de equilíbrio (receita) = custo fixo ÷ MC% | C17: =IF(C15>0,C16/C15,0) -> 175606.62 | D17: =IF(D15>0,D16/D15,0) -> 374038.21 | E17: =IF(E15>0,E16/E15,0) -> 552066.92 | F17: Fórmula do slide 15: receita mínima para não ter prejuízo no período.
B18: Ponto de equilíbrio em clientes pagantes (média por mês) | C18: =IF(C15>0,C17/12/Premissas!$C$17,0) -> 1.9511847 | D18: =IF(D15>0,D17/12/Premissas!$C$17,0) -> 4.1559801 | F18: Receita de equilíbrio do ano ÷ 12 ÷ ticket médio.
B19: Margem de segurança = (receita − PE) ÷ receita | C19: =IF(C8>0,(C8-C17)/C8,0) -> 0.71446078 | D19: =IF(D8>0,(D8-D17)/D8,0) -> 0.85669034 | E19: =IF(E8>0,(E8-E17)/E8,0) -> 0.82881646 | F19: Quanto a receita pode cair antes de dar prejuízo.
B20: Primeiro mês com resultado operacional positivo | C20: =IF(MIN('DRE Mensal'!D26:AA26)>24,"após o M24",MIN('DRE Mensal'!D26:AA26)) -> 4 | F20: Antes disso, o piloto não gera receita.
B21: Caixa
B22: Menor saldo de caixa no período | C22: =MIN('Fluxo de Caixa'!C24:AA24) -> 875.34565 | F22: Se fosse negativo, o aporte inicial não bastaria.
B23: Saldo de caixa no fim do período | C23: ='Fluxo de Caixa'!O24 -> 265500.73 | D23: ='Fluxo de Caixa'!AA24 -> 1843319.9 | E23: ='Fluxo de Caixa'!AA24 -> 1843319.9 | F23: Aba Fluxo de Caixa.
B24: Indicadores de SaaS
B25: Ticket médio mensal por cliente (ARPA) | C25: =Premissas!$C$17 -> 7500 | F25: 300 colaboradores × preço médio.
B26: CAC (custo para conquistar um cliente) | C26: =Premissas!$C$36 -> 3000 | F26: Premissas.
B27: Margem de contribuição por cliente/mês | C27: =C25*D15 -> 5438.3481 | F27: ARPA × MC% do Ano 2.
B28: LTV (valor do cliente ao longo da vida) | C28: =C27*Premissas!$C$58 -> 195780.53 | F28: MC por cliente × vida média estimada (36 meses).
B29: LTV ÷ CAC | C29: =C28/C26 -> 65.260177 | F29: Saudável: acima de 3x.
B30: Payback do CAC (meses) | C30: =C26/C27 -> 0.5516381 | F30: Meses de margem para recuperar o custo de conquistar o cliente.
B32: Gráfico do ponto de equilíbrio — mês típico do Ano 2
B33: Clientes pagantes no mês | C33: Receita | D33: Custo total | E33: Custo fixo
B34: 0 | C34: =B34*Premissas!$C$17 -> 0 | D34: ='DRE Anual'!E13/12+C34*(1-D15) -> 22601.667 | E34: ='DRE Anual'!E13/12 -> 22601.667
B35: 4 | C35: =B35*Premissas!$C$17 -> 30000 | D35: ='DRE Anual'!E13/12+C35*(1-D15) -> 30848.274 | E35: ='DRE Anual'!E13/12 -> 22601.667
B36: 8 | C36: =B36*Premissas!$C$17 -> 60000 | D36: ='DRE Anual'!E13/12+C36*(1-D15) -> 39094.882 | E36: ='DRE Anual'!E13/12 -> 22601.667
B37: 12 | C37: =B37*Premissas!$C$17 -> 90000 | D37: ='DRE Anual'!E13/12+C37*(1-D15) -> 47341.489 | E37: ='DRE Anual'!E13/12 -> 22601.667
B38: 16 | C38: =B38*Premissas!$C$17 -> 120000 | D38: ='DRE Anual'!E13/12+C38*(1-D15) -> 55588.097 | E38: ='DRE Anual'!E13/12 -> 22601.667
B39: 20 | C39: =B39*Premissas!$C$17 -> 150000 | D39: ='DRE Anual'!E13/12+C39*(1-D15) -> 63834.704 | E39: ='DRE Anual'!E13/12 -> 22601.667
B40: 24 | C40: =B40*Premissas!$C$17 -> 180000 | D40: ='DRE Anual'!E13/12+C40*(1-D15) -> 72081.312 | E40: ='DRE Anual'!E13/12 -> 22601.667
B41: 28 | C41: =B41*Premissas!$C$17 -> 210000 | D41: ='DRE Anual'!E13/12+C41*(1-D15) -> 80327.92 | E41: ='DRE Anual'!E13/12 -> 22601.667
B42: 32 | C42: =B42*Premissas!$C$17 -> 240000 | D42: ='DRE Anual'!E13/12+C42*(1-D15) -> 88574.527 | E42: ='DRE Anual'!E13/12 -> 22601.667
B43: 36 | C43: =B43*Premissas!$C$17 -> 270000 | D43: ='DRE Anual'!E13/12+C43*(1-D15) -> 96821.135 | E43: ='DRE Anual'!E13/12 -> 22601.667
B44: 40 | C44: =B44*Premissas!$C$17 -> 300000 | D44: ='DRE Anual'!E13/12+C44*(1-D15) -> 105067.74 | E44: ='DRE Anual'!E13/12 -> 22601.667
B45: Equilíbrio no mês típico do Ano 2 (clientes) | C45: ='DRE Anual'!E13/12/(Premissas!$C$17*D15) -> 4.1559801
B47: Clientes necessários para cobrir o custo fixo de cada fase
B48: Fase | C48: Custo fixo + depreciação/mês | D48: Clientes no equilíbrio | E48: Clientes previstos no fim da fase
B49: Fase 1 · Piloto | C49: ='Custos Fixos'!C30+'Custos Fixos'!C33 -> 2601.6667 | D49: =C49/(Premissas!$C$17*$E$15) -> 0.47527145 | E49: =INDEX('Receita e Clientes'!D11:AA11,Premissas!$C$30) -> 0
B50: Fase 2 · Early adopters | C50: ='Custos Fixos'!D30+'Custos Fixos'!D33 -> 7101.6667 | D50: =C50/(Premissas!$C$17*$E$15) -> 1.2973297 | E50: =INDEX('Receita e Clientes'!D11:AA11,Premissas!$C$31) -> 10
B51: Fase 3a · Scale inicial | C51: ='Custos Fixos'!E30+'Custos Fixos'!E33 -> 14101.667 | D51: =C51/(Premissas!$C$17*$E$15) -> 2.576087 | E51: =INDEX('Receita e Clientes'!D11:AA11,Premissas!$C$32) -> 28
B52: Fase 3b · Scale maduro | C52: ='Custos Fixos'!F30+'Custos Fixos'!F33 -> 19101.667 | D52: =C52/(Premissas!$C$17*$E$15) -> 3.489485 | E52: =INDEX('Receita e Clientes'!D11:AA11,24) -> 40
B53: Sem contar o CAC: é o equilíbrio da operação já instalada. Usa a MC% média dos 24 meses.

Sheet Cenários
B2: Cenários: pessimista, base e otimista
B3: Foto dos resultados com o seletor da aba Premissas em 1, 2 e 3. A coluna "Agora" acompanha o seletor ao vivo.
B5: Resultado | C5: Pessimista | D5: Base | E5: Otimista | F5: Agora (ao vivo) | G5: O que muda
B6: Clientes pagantes no M24 | C6: 21.391937 | D6: 40 | E6: 51.1 | F6: ='Receita e Clientes'!AA11 -> 40 | G6: Pessimista: 40% menos leads, 8% de desconto, CAC 30% maior e 2% de cancelamento ao mês no Ano 2. Otimista: 30% mais leads e CAC 10% menor.
B7: Receita em 24 meses | C7: 1800866 | D7: 3225000 | E7: 4050750 | F7: =Indicadores!E8 -> 3225000
B8: Resultado líquido — Ano 1 | C8: 186173.91 | D8: 328990.73 | E8: 414417.38 | F8: =Indicadores!C9 -> 328990.73
B9: Resultado líquido — Ano 2 | C9: 803470.5 | D9: 1703065.9 | E9: 2207244.7 | F9: =Indicadores!D9 -> 1703065.9
B10: Margem de contribuição (24m) | C10: 0.73731308 | D10: 0.72987529 | E10: 0.72541792 | F10: =Indicadores!E15 -> 0.72987529
B11: Primeiro mês com resultado positivo | C11: 4 | D11: 4 | E11: 4 | F11: =Indicadores!C20 -> 4
B12: Retorno do investimento | C12: 7 | D12: 7 | E12: 7 | F12: =Indicadores!C12 -> 7
B13: Menor saldo de caixa | C13: 875.34565 | D13: 875.34565 | E13: 875.34565 | F13: =Indicadores!C22 -> 875.34565
B14: Saldo de caixa no M24 | C14: 911164 | D14: 1843319.9 | E14: 2373752.3 | F14: =Indicadores!D23 -> 1843319.9
B15: LTV ÷ CAC | C15: 46.66488 | D15: 65.260177 | E15: 72.043522 | F15: =Indicadores!C29 -> 65.260177
B17: As colunas Pessimista, Base e Otimista são valores fixos: para atualizá-las depois de mudar uma premissa, ponha o seletor em 1, 2 e 3 e copie a coluna "Agora".

Sheet Comparáveis
B2: Comparáveis de mercado
B3: Dados reais (não fictícios) usados para calibrar as metas do SkillWay — os mesmos da Seção 20.
B5: Empresa | C5: Modelo | D5: Marco real reportado | E5: Fonte
B6: Scaleup | C6: Capacitação empreendedora (B2C, alto volume) | D6: R$ 3 milhões de faturamento já no 1º ano | E6: Baguete
B7: Witseed | C7: Educação corporativa B2B (HRAcademy) | D7: Aporte seed de R$ 920 mil após ~4 anos; equipe de 15 para 27 pessoas | E7: Baguete
B8: Education Journey | C8: Curadoria de trilhas para empresas — o modelo mais próximo do SkillWay | D8: Contrato com a Ambev (4 mil cursos) ainda em estágio inicial | E8: Forbes Brasil
B9: Gupy | C9: HRTech (recrutamento → suíte completa) | D9: 15% de crescimento médio mensal da receita até a Série A | E9: LAVCA
B10: Sólides | C10: RH comportamental para PME (concorrente, Seção 3) | D10: 45 mil clientes, com aporte de R$ 530 mi e aquisições | E10: Seção 3
B12: Benchmarks de SaaS B2B brasileiro
B13: • MRR mediano em estágio pré-seed: ~R$ 15 mil (o SkillWay passa disso com 2 clientes pagantes).
B14: • CAC típico PME: R$ 3 mil a R$ 15 mil · mid-market: R$ 30 mil a R$ 150 mil.
B15: • LTV/CAC saudável: 3x ou mais.
B16: • Churn mensal mediano: 7,5% no pré-seed a 1% em empresas maduras (caso Gupy).
